<?xml version="1.0" encoding="utf-8" ?><x:xmpmeta xmlns:x="adobe:ns:meta/" ><rdf:RDF xmlns:rdf="http://www.w3.org/1999/02/22-rdf-syntax-ns#" xmlns:xmp="http://ns.adobe.com/xap/1.0/" xmlns:xmpDM="http://ns.adobe.com/xmp/1.0/DynamicMedia/" xmlns:xmpG="http://ns.adobe.com/xap/1.0/g/" xmlns:tsc="http://www.techsmith.com/xmp/tsc/" xmlns:tscDM="http://www.techsmith.com/xmp/tscDM/" xmlns:tscHS="http://www.techsmith.com/xmp/tscHS/" xmlns:stDim="http://ns.adobe.com/xap/1.0/sType/Dimensions#" xmlns:stFnt="http://ns.adobe.com/xap/1.0/sType/Font#" xmlns:dc="http://purl.org/dc/elements/1.1/" ><rdf:Description tsc:version="2.0.0" dc:title="copyediting vs comprehensive editing" dc:date="2017-12-19T15:12:44-6:00" dc:creator="" dc:Description="" dc:source="Camtasia Mac - 2.10.2" tscDM:iPodExplicit="false" tscDM:keywords="" tscDM:thumbnail="" tscDM:firstFrame="" ><xmpDM:duration xmpDM:scale="1/1000" xmpDM:value="727233" ></xmpDM:duration><xmpDM:videoFrameSize stDim:unit="pixel" stDim:w="1152" stDim:h="720" ></xmpDM:videoFrameSize><tsc:langName><rdf:Bag><rdf:li xml:lang="en">English</rdf:li><rdf:li xml:lang="en-US">English</rdf:li></rdf:Bag></tsc:langName><xmpDM:Tracks><rdf:Bag><rdf:li><rdf:Description xmpDM:trackType="Caption" xmpDM:frameRate="f1000" xmpDM:trackName="Captioning" stFnt:fontFamily="Arial" tscDM:fontSize="32" tscDM:bgOpacity="0.8" tscDM:position="overlay" tscDM:captionbarheight="46" ><xmpDM:markers><rdf:Seq><rdf:li><rdf:Description xmpDM:startTime="0" xmpDM:duration="1000" tscDM:valign="bottom" tscDM:halign="center" ><xmpDM:name><rdf:Alt><rdf:li xml:lang="en">{\rtf1 }</rdf:li></rdf:Alt></xmpDM:name></rdf:Description></rdf:li><rdf:li><rdf:Description xmpDM:startTime="1000" xmpDM:duration="3533" tscDM:valign="bottom" tscDM:halign="center" ><xmpDM:name><rdf:Alt><rdf:li xml:lang="en">{\rtf1 hi and welcome to te cm 5195}</rdf:li></rdf:Alt></xmpDM:name></rdf:Description></rdf:li><rdf:li><rdf:Description xmpDM:startTime="4533" xmpDM:duration="2466" tscDM:valign="bottom" tscDM:halign="center" ><xmpDM:name><rdf:Alt><rdf:li xml:lang="en">{\rtf1 so today what we&apos;ll talk about is}</rdf:li></rdf:Alt></xmpDM:name></rdf:Description></rdf:li><rdf:li><rdf:Description xmpDM:startTime="7000" xmpDM:duration="1800" tscDM:valign="bottom" tscDM:halign="center" ><xmpDM:name><rdf:Alt><rdf:li xml:lang="en">{\rtf1 differentiating copy editing and}</rdf:li></rdf:Alt></xmpDM:name></rdf:Description></rdf:li><rdf:li><rdf:Description xmpDM:startTime="8800" xmpDM:duration="2566" tscDM:valign="bottom" tscDM:halign="center" ><xmpDM:name><rdf:Alt><rdf:li xml:lang="en">{\rtf1 comprehensive editing and really looking}</rdf:li></rdf:Alt></xmpDM:name></rdf:Description></rdf:li><rdf:li><rdf:Description xmpDM:startTime="11366" xmpDM:duration="2300" tscDM:valign="bottom" tscDM:halign="center" ><xmpDM:name><rdf:Alt><rdf:li xml:lang="en">{\rtf1 at the to sort of from a really broad}</rdf:li></rdf:Alt></xmpDM:name></rdf:Description></rdf:li><rdf:li><rdf:Description xmpDM:startTime="13666" xmpDM:duration="3233" tscDM:valign="bottom" tscDM:halign="center" ><xmpDM:name><rdf:Alt><rdf:li xml:lang="en">{\rtf1 perspective so just a little context}</rdf:li></rdf:Alt></xmpDM:name></rdf:Description></rdf:li><rdf:li><rdf:Description xmpDM:startTime="16900" xmpDM:duration="1700" tscDM:valign="bottom" tscDM:halign="center" ><xmpDM:name><rdf:Alt><rdf:li xml:lang="en">{\rtf1 we&apos;ve been walking through copy editing}</rdf:li></rdf:Alt></xmpDM:name></rdf:Description></rdf:li><rdf:li><rdf:Description xmpDM:startTime="18600" xmpDM:duration="3133" tscDM:valign="bottom" tscDM:halign="center" ><xmpDM:name><rdf:Alt><rdf:li xml:lang="en">{\rtf1 and this this week will serve as a}</rdf:li></rdf:Alt></xmpDM:name></rdf:Description></rdf:li><rdf:li><rdf:Description xmpDM:startTime="21733" xmpDM:duration="4200" tscDM:valign="bottom" tscDM:halign="center" ><xmpDM:name><rdf:Alt><rdf:li xml:lang="en">{\rtf1 bridge to moving into more comprehensive}</rdf:li></rdf:Alt></xmpDM:name></rdf:Description></rdf:li><rdf:li><rdf:Description xmpDM:startTime="25933" xmpDM:duration="2633" tscDM:valign="bottom" tscDM:halign="center" ><xmpDM:name><rdf:Alt><rdf:li xml:lang="en">{\rtf1 editing activities just as a reminder I}</rdf:li></rdf:Alt></xmpDM:name></rdf:Description></rdf:li><rdf:li><rdf:Description xmpDM:startTime="28566" xmpDM:duration="1500" tscDM:valign="bottom" tscDM:halign="center" ><xmpDM:name><rdf:Alt><rdf:li xml:lang="en">{\rtf1 showed you this on the first week of}</rdf:li></rdf:Alt></xmpDM:name></rdf:Description></rdf:li><rdf:li><rdf:Description xmpDM:startTime="30066" xmpDM:duration="2933" tscDM:valign="bottom" tscDM:halign="center" ><xmpDM:name><rdf:Alt><rdf:li xml:lang="en">{\rtf1 class this picture of this pyramid and I}</rdf:li></rdf:Alt></xmpDM:name></rdf:Description></rdf:li><rdf:li><rdf:Description xmpDM:startTime="33000" xmpDM:duration="2233" tscDM:valign="bottom" tscDM:halign="center" ><xmpDM:name><rdf:Alt><rdf:li xml:lang="en">{\rtf1 really talked about different levels of}</rdf:li></rdf:Alt></xmpDM:name></rdf:Description></rdf:li><rdf:li><rdf:Description xmpDM:startTime="35233" xmpDM:duration="3666" tscDM:valign="bottom" tscDM:halign="center" ><xmpDM:name><rdf:Alt><rdf:li xml:lang="en">{\rtf1 editing so I just wanted to remind you}</rdf:li></rdf:Alt></xmpDM:name></rdf:Description></rdf:li><rdf:li><rdf:Description xmpDM:startTime="38900" xmpDM:duration="3666" tscDM:valign="bottom" tscDM:halign="center" ><xmpDM:name><rdf:Alt><rdf:li xml:lang="en">{\rtf1 kind of some context of what we&apos;re work}</rdf:li></rdf:Alt></xmpDM:name></rdf:Description></rdf:li><rdf:li><rdf:Description xmpDM:startTime="42566" xmpDM:duration="1366" tscDM:valign="bottom" tscDM:halign="center" ><xmpDM:name><rdf:Alt><rdf:li xml:lang="en">{\rtf1 what we&apos;re going to walk through so}</rdf:li></rdf:Alt></xmpDM:name></rdf:Description></rdf:li><rdf:li><rdf:Description xmpDM:startTime="43933" xmpDM:duration="1700" tscDM:valign="bottom" tscDM:halign="center" ><xmpDM:name><rdf:Alt><rdf:li xml:lang="en">{\rtf1 we&apos;ve been walking through copy editing}</rdf:li></rdf:Alt></xmpDM:name></rdf:Description></rdf:li><rdf:li><rdf:Description xmpDM:startTime="45633" xmpDM:duration="2366" tscDM:valign="bottom" tscDM:halign="center" ><xmpDM:name><rdf:Alt><rdf:li xml:lang="en">{\rtf1 we&apos;re going to move sort of toward}</rdf:li></rdf:Alt></xmpDM:name></rdf:Description></rdf:li><rdf:li><rdf:Description xmpDM:startTime="48000" xmpDM:duration="2400" tscDM:valign="bottom" tscDM:halign="center" ><xmpDM:name><rdf:Alt><rdf:li xml:lang="en">{\rtf1 comprehensive editing well within these}</rdf:li></rdf:Alt></xmpDM:name></rdf:Description></rdf:li><rdf:li><rdf:Description xmpDM:startTime="50400" xmpDM:duration="2033" tscDM:valign="bottom" tscDM:halign="center" ><xmpDM:name><rdf:Alt><rdf:li xml:lang="en">{\rtf1 different levels of editing and as we&apos;ll}</rdf:li></rdf:Alt></xmpDM:name></rdf:Description></rdf:li><rdf:li><rdf:Description xmpDM:startTime="52433" xmpDM:duration="2033" tscDM:valign="bottom" tscDM:halign="center" ><xmpDM:name><rdf:Alt><rdf:li xml:lang="en">{\rtf1 see there&apos;s a lot of overlap between the}</rdf:li></rdf:Alt></xmpDM:name></rdf:Description></rdf:li><rdf:li><rdf:Description xmpDM:startTime="54466" xmpDM:duration="2000" tscDM:valign="bottom" tscDM:halign="center" ><xmpDM:name><rdf:Alt><rdf:li xml:lang="en">{\rtf1 two and so I want to give you a little}</rdf:li></rdf:Alt></xmpDM:name></rdf:Description></rdf:li><rdf:li><rdf:Description xmpDM:startTime="56466" xmpDM:duration="2800" tscDM:valign="bottom" tscDM:halign="center" ><xmpDM:name><rdf:Alt><rdf:li xml:lang="en">{\rtf1 bit of insight into why the course is is}</rdf:li></rdf:Alt></xmpDM:name></rdf:Description></rdf:li><rdf:li><rdf:Description xmpDM:startTime="59266" xmpDM:duration="4766" tscDM:valign="bottom" tscDM:halign="center" ><xmpDM:name><rdf:Alt><rdf:li xml:lang="en">{\rtf1 structured the way it is}</rdf:li></rdf:Alt></xmpDM:name></rdf:Description></rdf:li><rdf:li><rdf:Description xmpDM:startTime="64033" xmpDM:duration="4900" tscDM:valign="bottom" tscDM:halign="center" ><xmpDM:name><rdf:Alt><rdf:li xml:lang="en">{\rtf1 so just also as a matter of review we}</rdf:li></rdf:Alt></xmpDM:name></rdf:Description></rdf:li><rdf:li><rdf:Description xmpDM:startTime="68933" xmpDM:duration="2400" tscDM:valign="bottom" tscDM:halign="center" ><xmpDM:name><rdf:Alt><rdf:li xml:lang="en">{\rtf1 talked about how editing the copy}</rdf:li></rdf:Alt></xmpDM:name></rdf:Description></rdf:li><rdf:li><rdf:Description xmpDM:startTime="71333" xmpDM:duration="3066" tscDM:valign="bottom" tscDM:halign="center" ><xmpDM:name><rdf:Alt><rdf:li xml:lang="en">{\rtf1 editing and editing in general being on}</rdf:li></rdf:Alt></xmpDM:name></rdf:Description></rdf:li><rdf:li><rdf:Description xmpDM:startTime="74400" xmpDM:duration="2700" tscDM:valign="bottom" tscDM:halign="center" ><xmpDM:name><rdf:Alt><rdf:li xml:lang="en">{\rtf1 a continual and so copy editing here on}</rdf:li></rdf:Alt></xmpDM:name></rdf:Description></rdf:li><rdf:li><rdf:Description xmpDM:startTime="77100" xmpDM:duration="2900" tscDM:valign="bottom" tscDM:halign="center" ><xmpDM:name><rdf:Alt><rdf:li xml:lang="en">{\rtf1 the left is more objective requires less}</rdf:li></rdf:Alt></xmpDM:name></rdf:Description></rdf:li><rdf:li><rdf:Description xmpDM:startTime="80000" xmpDM:duration="3266" tscDM:valign="bottom" tscDM:halign="center" ><xmpDM:name><rdf:Alt><rdf:li xml:lang="en">{\rtf1 editorial judgment and as we move along}</rdf:li></rdf:Alt></xmpDM:name></rdf:Description></rdf:li><rdf:li><rdf:Description xmpDM:startTime="83266" xmpDM:duration="2233" tscDM:valign="bottom" tscDM:halign="center" ><xmpDM:name><rdf:Alt><rdf:li xml:lang="en">{\rtf1 these are not again this is not a}</rdf:li></rdf:Alt></xmpDM:name></rdf:Description></rdf:li><rdf:li><rdf:Description xmpDM:startTime="85500" xmpDM:duration="2566" tscDM:valign="bottom" tscDM:halign="center" ><xmpDM:name><rdf:Alt><rdf:li xml:lang="en">{\rtf1 comprehensive list of editing activities}</rdf:li></rdf:Alt></xmpDM:name></rdf:Description></rdf:li><rdf:li><rdf:Description xmpDM:startTime="88066" xmpDM:duration="2600" tscDM:valign="bottom" tscDM:halign="center" ><xmpDM:name><rdf:Alt><rdf:li xml:lang="en">{\rtf1 but as we move along the continuum we&apos;ve}</rdf:li></rdf:Alt></xmpDM:name></rdf:Description></rdf:li><rdf:li><rdf:Description xmpDM:startTime="90666" xmpDM:duration="2133" tscDM:valign="bottom" tscDM:halign="center" ><xmpDM:name><rdf:Alt><rdf:li xml:lang="en">{\rtf1 got things like style and tone editing}</rdf:li></rdf:Alt></xmpDM:name></rdf:Description></rdf:li><rdf:li><rdf:Description xmpDM:startTime="92800" xmpDM:duration="1666" tscDM:valign="bottom" tscDM:halign="center" ><xmpDM:name><rdf:Alt><rdf:li xml:lang="en">{\rtf1 for style and tone that requires a bit}</rdf:li></rdf:Alt></xmpDM:name></rdf:Description></rdf:li><rdf:li><rdf:Description xmpDM:startTime="94466" xmpDM:duration="5900" tscDM:valign="bottom" tscDM:halign="center" ><xmpDM:name><rdf:Alt><rdf:li xml:lang="en">{\rtf1 more a bit more judgment organization}</rdf:li></rdf:Alt></xmpDM:name></rdf:Description></rdf:li><rdf:li><rdf:Description xmpDM:startTime="100366" xmpDM:duration="1733" tscDM:valign="bottom" tscDM:halign="center" ><xmpDM:name><rdf:Alt><rdf:li xml:lang="en">{\rtf1 requires a bit more judgment and then}</rdf:li></rdf:Alt></xmpDM:name></rdf:Description></rdf:li><rdf:li><rdf:Description xmpDM:startTime="102100" xmpDM:duration="2566" tscDM:valign="bottom" tscDM:halign="center" ><xmpDM:name><rdf:Alt><rdf:li xml:lang="en">{\rtf1 full-blown comprehensively editing the}</rdf:li></rdf:Alt></xmpDM:name></rdf:Description></rdf:li><rdf:li><rdf:Description xmpDM:startTime="104666" xmpDM:duration="3633" tscDM:valign="bottom" tscDM:halign="center" ><xmpDM:name><rdf:Alt><rdf:li xml:lang="en">{\rtf1 entire document as much more subjective}</rdf:li></rdf:Alt></xmpDM:name></rdf:Description></rdf:li><rdf:li><rdf:Description xmpDM:startTime="108300" xmpDM:duration="2300" tscDM:valign="bottom" tscDM:halign="center" ><xmpDM:name><rdf:Alt><rdf:li xml:lang="en">{\rtf1 has less rules and requires the most}</rdf:li></rdf:Alt></xmpDM:name></rdf:Description></rdf:li><rdf:li><rdf:Description xmpDM:startTime="110600" xmpDM:duration="2600" tscDM:valign="bottom" tscDM:halign="center" ><xmpDM:name><rdf:Alt><rdf:li xml:lang="en">{\rtf1 editorial judgment so just give you a}</rdf:li></rdf:Alt></xmpDM:name></rdf:Description></rdf:li><rdf:li><rdf:Description xmpDM:startTime="113200" xmpDM:duration="2466" tscDM:valign="bottom" tscDM:halign="center" ><xmpDM:name><rdf:Alt><rdf:li xml:lang="en">{\rtf1 little bit of a framework for where}</rdf:li></rdf:Alt></xmpDM:name></rdf:Description></rdf:li><rdf:li><rdf:Description xmpDM:startTime="115666" xmpDM:duration="3933" tscDM:valign="bottom" tscDM:halign="center" ><xmpDM:name><rdf:Alt><rdf:li xml:lang="en">{\rtf1 we&apos;re moving in this course so some of}</rdf:li></rdf:Alt></xmpDM:name></rdf:Description></rdf:li><rdf:li><rdf:Description xmpDM:startTime="119600" xmpDM:duration="1900" tscDM:valign="bottom" tscDM:halign="center" ><xmpDM:name><rdf:Alt><rdf:li xml:lang="en">{\rtf1 the and again this is not all of the}</rdf:li></rdf:Alt></xmpDM:name></rdf:Description></rdf:li><rdf:li><rdf:Description xmpDM:startTime="121500" xmpDM:duration="2566" tscDM:valign="bottom" tscDM:halign="center" ><xmpDM:name><rdf:Alt><rdf:li xml:lang="en">{\rtf1 style and tone things we&apos;ll cover in}</rdf:li></rdf:Alt></xmpDM:name></rdf:Description></rdf:li><rdf:li><rdf:Description xmpDM:startTime="124066" xmpDM:duration="2266" tscDM:valign="bottom" tscDM:halign="center" ><xmpDM:name><rdf:Alt><rdf:li xml:lang="en">{\rtf1 this course but I wanted to give you}</rdf:li></rdf:Alt></xmpDM:name></rdf:Description></rdf:li><rdf:li><rdf:Description xmpDM:startTime="126333" xmpDM:duration="2800" tscDM:valign="bottom" tscDM:halign="center" ><xmpDM:name><rdf:Alt><rdf:li xml:lang="en">{\rtf1 some examples of style and tone editing}</rdf:li></rdf:Alt></xmpDM:name></rdf:Description></rdf:li><rdf:li><rdf:Description xmpDM:startTime="129133" xmpDM:duration="2433" tscDM:valign="bottom" tscDM:halign="center" ><xmpDM:name><rdf:Alt><rdf:li xml:lang="en">{\rtf1 so we&apos;ll learn to edit Fork}</rdf:li></rdf:Alt></xmpDM:name></rdf:Description></rdf:li><rdf:li><rdf:Description xmpDM:startTime="131566" xmpDM:duration="2266" tscDM:valign="bottom" tscDM:halign="center" ><xmpDM:name><rdf:Alt><rdf:li xml:lang="en">{\rtf1 sites conciseness right and so this is}</rdf:li></rdf:Alt></xmpDM:name></rdf:Description></rdf:li><rdf:li><rdf:Description xmpDM:startTime="133833" xmpDM:duration="2366" tscDM:valign="bottom" tscDM:halign="center" ><xmpDM:name><rdf:Alt><rdf:li xml:lang="en">{\rtf1 really at the word and perhaps at the}</rdf:li></rdf:Alt></xmpDM:name></rdf:Description></rdf:li><rdf:li><rdf:Description xmpDM:startTime="136200" xmpDM:duration="3733" tscDM:valign="bottom" tscDM:halign="center" ><xmpDM:name><rdf:Alt><rdf:li xml:lang="en">{\rtf1 sentence level as well but this example}</rdf:li></rdf:Alt></xmpDM:name></rdf:Description></rdf:li><rdf:li><rdf:Description xmpDM:startTime="139933" xmpDM:duration="3066" tscDM:valign="bottom" tscDM:halign="center" ><xmpDM:name><rdf:Alt><rdf:li xml:lang="en">{\rtf1 here is a specific example of a awarding}</rdf:li></rdf:Alt></xmpDM:name></rdf:Description></rdf:li><rdf:li><rdf:Description xmpDM:startTime="143000" xmpDM:duration="2566" tscDM:valign="bottom" tscDM:halign="center" ><xmpDM:name><rdf:Alt><rdf:li xml:lang="en">{\rtf1 this issue so if we take a sentence like}</rdf:li></rdf:Alt></xmpDM:name></rdf:Description></rdf:li><rdf:li><rdf:Description xmpDM:startTime="145566" xmpDM:duration="2566" tscDM:valign="bottom" tscDM:halign="center" ><xmpDM:name><rdf:Alt><rdf:li xml:lang="en">{\rtf1 the report is an analysis of the problem}</rdf:li></rdf:Alt></xmpDM:name></rdf:Description></rdf:li><rdf:li><rdf:Description xmpDM:startTime="148133" xmpDM:duration="2866" tscDM:valign="bottom" tscDM:halign="center" ><xmpDM:name><rdf:Alt><rdf:li xml:lang="en">{\rtf1 that&apos;s a particularly wordy sentence}</rdf:li></rdf:Alt></xmpDM:name></rdf:Description></rdf:li><rdf:li><rdf:Description xmpDM:startTime="151000" xmpDM:duration="3266" tscDM:valign="bottom" tscDM:halign="center" ><xmpDM:name><rdf:Alt><rdf:li xml:lang="en">{\rtf1 that doesn&apos;t need to be wordy and so we}</rdf:li></rdf:Alt></xmpDM:name></rdf:Description></rdf:li><rdf:li><rdf:Description xmpDM:startTime="154266" xmpDM:duration="1733" tscDM:valign="bottom" tscDM:halign="center" ><xmpDM:name><rdf:Alt><rdf:li xml:lang="en">{\rtf1 can take a strategy like converting the}</rdf:li></rdf:Alt></xmpDM:name></rdf:Description></rdf:li><rdf:li><rdf:Description xmpDM:startTime="156000" xmpDM:duration="3066" tscDM:valign="bottom" tscDM:halign="center" ><xmpDM:name><rdf:Alt><rdf:li xml:lang="en">{\rtf1 noun analysis into a main verb and our}</rdf:li></rdf:Alt></xmpDM:name></rdf:Description></rdf:li><rdf:li><rdf:Description xmpDM:startTime="159066" xmpDM:duration="2733" tscDM:valign="bottom" tscDM:halign="center" ><xmpDM:name><rdf:Alt><rdf:li xml:lang="en">{\rtf1 revision looks like this report analyzes}</rdf:li></rdf:Alt></xmpDM:name></rdf:Description></rdf:li><rdf:li><rdf:Description xmpDM:startTime="161800" xmpDM:duration="2300" tscDM:valign="bottom" tscDM:halign="center" ><xmpDM:name><rdf:Alt><rdf:li xml:lang="en">{\rtf1 the problem right so instead of is an}</rdf:li></rdf:Alt></xmpDM:name></rdf:Description></rdf:li><rdf:li><rdf:Description xmpDM:startTime="164100" xmpDM:duration="2633" tscDM:valign="bottom" tscDM:halign="center" ><xmpDM:name><rdf:Alt><rdf:li xml:lang="en">{\rtf1 analysis of the problem we say the court}</rdf:li></rdf:Alt></xmpDM:name></rdf:Description></rdf:li><rdf:li><rdf:Description xmpDM:startTime="166733" xmpDM:duration="1966" tscDM:valign="bottom" tscDM:halign="center" ><xmpDM:name><rdf:Alt><rdf:li xml:lang="en">{\rtf1 analyzes the problem so that&apos;s an}</rdf:li></rdf:Alt></xmpDM:name></rdf:Description></rdf:li><rdf:li><rdf:Description xmpDM:startTime="168700" xmpDM:duration="4666" tscDM:valign="bottom" tscDM:halign="center" ><xmpDM:name><rdf:Alt><rdf:li xml:lang="en">{\rtf1 example of a style edit making something}</rdf:li></rdf:Alt></xmpDM:name></rdf:Description></rdf:li><rdf:li><rdf:Description xmpDM:startTime="173366" xmpDM:duration="2166" tscDM:valign="bottom" tscDM:halign="center" ><xmpDM:name><rdf:Alt><rdf:li xml:lang="en">{\rtf1 more concise and so again just to remind}</rdf:li></rdf:Alt></xmpDM:name></rdf:Description></rdf:li><rdf:li><rdf:Description xmpDM:startTime="175533" xmpDM:duration="1933" tscDM:valign="bottom" tscDM:halign="center" ><xmpDM:name><rdf:Alt><rdf:li xml:lang="en">{\rtf1 you that there&apos;s nothing incorrect about}</rdf:li></rdf:Alt></xmpDM:name></rdf:Description></rdf:li><rdf:li><rdf:Description xmpDM:startTime="177466" xmpDM:duration="5033" tscDM:valign="bottom" tscDM:halign="center" ><xmpDM:name><rdf:Alt><rdf:li xml:lang="en">{\rtf1 the wordy sentence grammatically but it}</rdf:li></rdf:Alt></xmpDM:name></rdf:Description></rdf:li><rdf:li><rdf:Description xmpDM:startTime="182500" xmpDM:duration="2566" tscDM:valign="bottom" tscDM:halign="center" ><xmpDM:name><rdf:Alt><rdf:li xml:lang="en">{\rtf1 actually is it serves the reader better}</rdf:li></rdf:Alt></xmpDM:name></rdf:Description></rdf:li><rdf:li><rdf:Description xmpDM:startTime="185066" xmpDM:duration="4166" tscDM:valign="bottom" tscDM:halign="center" ><xmpDM:name><rdf:Alt><rdf:li xml:lang="en">{\rtf1 because it&apos;s more concise another}</rdf:li></rdf:Alt></xmpDM:name></rdf:Description></rdf:li><rdf:li><rdf:Description xmpDM:startTime="189233" xmpDM:duration="1933" tscDM:valign="bottom" tscDM:halign="center" ><xmpDM:name><rdf:Alt><rdf:li xml:lang="en">{\rtf1 example is active versus passive voice}</rdf:li></rdf:Alt></xmpDM:name></rdf:Description></rdf:li><rdf:li><rdf:Description xmpDM:startTime="191166" xmpDM:duration="1733" tscDM:valign="bottom" tscDM:halign="center" ><xmpDM:name><rdf:Alt><rdf:li xml:lang="en">{\rtf1 so now we&apos;re definitely at the sentence}</rdf:li></rdf:Alt></xmpDM:name></rdf:Description></rdf:li><rdf:li><rdf:Description xmpDM:startTime="192900" xmpDM:duration="2433" tscDM:valign="bottom" tscDM:halign="center" ><xmpDM:name><rdf:Alt><rdf:li xml:lang="en">{\rtf1 level right so so editing editing}</rdf:li></rdf:Alt></xmpDM:name></rdf:Description></rdf:li><rdf:li><rdf:Description xmpDM:startTime="195333" xmpDM:duration="5400" tscDM:valign="bottom" tscDM:halign="center" ><xmpDM:name><rdf:Alt><rdf:li xml:lang="en">{\rtf1 sentences in particular formats or}</rdf:li></rdf:Alt></xmpDM:name></rdf:Description></rdf:li><rdf:li><rdf:Description xmpDM:startTime="200733" xmpDM:duration="2900" tscDM:valign="bottom" tscDM:halign="center" ><xmpDM:name><rdf:Alt><rdf:li xml:lang="en">{\rtf1 structures so passive voice might be the}</rdf:li></rdf:Alt></xmpDM:name></rdf:Description></rdf:li><rdf:li><rdf:Description xmpDM:startTime="203633" xmpDM:duration="2933" tscDM:valign="bottom" tscDM:halign="center" ><xmpDM:name><rdf:Alt><rdf:li xml:lang="en">{\rtf1 test tube&apos;s were fill&apos;d active voice}</rdf:li></rdf:Alt></xmpDM:name></rdf:Description></rdf:li><rdf:li><rdf:Description xmpDM:startTime="206566" xmpDM:duration="1800" tscDM:valign="bottom" tscDM:halign="center" ><xmpDM:name><rdf:Alt><rdf:li xml:lang="en">{\rtf1 might be the chemical of the test tube&apos;s}</rdf:li></rdf:Alt></xmpDM:name></rdf:Description></rdf:li><rdf:li><rdf:Description xmpDM:startTime="208366" xmpDM:duration="2633" tscDM:valign="bottom" tscDM:halign="center" ><xmpDM:name><rdf:Alt><rdf:li xml:lang="en">{\rtf1 right and so as an editor we need to be}</rdf:li></rdf:Alt></xmpDM:name></rdf:Description></rdf:li><rdf:li><rdf:Description xmpDM:startTime="211000" xmpDM:duration="1733" tscDM:valign="bottom" tscDM:halign="center" ><xmpDM:name><rdf:Alt><rdf:li xml:lang="en">{\rtf1 able to identify passive and active}</rdf:li></rdf:Alt></xmpDM:name></rdf:Description></rdf:li><rdf:li><rdf:Description xmpDM:startTime="212733" xmpDM:duration="3600" tscDM:valign="bottom" tscDM:halign="center" ><xmpDM:name><rdf:Alt><rdf:li xml:lang="en">{\rtf1 voice we also need to know why and when}</rdf:li></rdf:Alt></xmpDM:name></rdf:Description></rdf:li><rdf:li><rdf:Description xmpDM:startTime="216333" xmpDM:duration="2166" tscDM:valign="bottom" tscDM:halign="center" ><xmpDM:name><rdf:Alt><rdf:li xml:lang="en">{\rtf1 we should use passive or active voice so}</rdf:li></rdf:Alt></xmpDM:name></rdf:Description></rdf:li><rdf:li><rdf:Description xmpDM:startTime="218500" xmpDM:duration="3666" tscDM:valign="bottom" tscDM:halign="center" ><xmpDM:name><rdf:Alt><rdf:li xml:lang="en">{\rtf1 this is a scientific report that we&apos;re}</rdf:li></rdf:Alt></xmpDM:name></rdf:Description></rdf:li><rdf:li><rdf:Description xmpDM:startTime="222166" xmpDM:duration="2400" tscDM:valign="bottom" tscDM:halign="center" ><xmpDM:name><rdf:Alt><rdf:li xml:lang="en">{\rtf1 editing the passive voice might be}</rdf:li></rdf:Alt></xmpDM:name></rdf:Description></rdf:li><rdf:li><rdf:Description xmpDM:startTime="224566" xmpDM:duration="2500" tscDM:valign="bottom" tscDM:halign="center" ><xmpDM:name><rdf:Alt><rdf:li xml:lang="en">{\rtf1 better right so we don&apos;t really care or}</rdf:li></rdf:Alt></xmpDM:name></rdf:Description></rdf:li><rdf:li><rdf:Description xmpDM:startTime="227066" xmpDM:duration="1466" tscDM:valign="bottom" tscDM:halign="center" ><xmpDM:name><rdf:Alt><rdf:li xml:lang="en">{\rtf1 the audience doesn&apos;t really care too}</rdf:li></rdf:Alt></xmpDM:name></rdf:Description></rdf:li><rdf:li><rdf:Description xmpDM:startTime="228533" xmpDM:duration="1866" tscDM:valign="bottom" tscDM:halign="center" ><xmpDM:name><rdf:Alt><rdf:li xml:lang="en">{\rtf1 much about the chemist they care about}</rdf:li></rdf:Alt></xmpDM:name></rdf:Description></rdf:li><rdf:li><rdf:Description xmpDM:startTime="230400" xmpDM:duration="2700" tscDM:valign="bottom" tscDM:halign="center" ><xmpDM:name><rdf:Alt><rdf:li xml:lang="en">{\rtf1 what the process is right and so in that}</rdf:li></rdf:Alt></xmpDM:name></rdf:Description></rdf:li><rdf:li><rdf:Description xmpDM:startTime="233100" xmpDM:duration="1300" tscDM:valign="bottom" tscDM:halign="center" ><xmpDM:name><rdf:Alt><rdf:li xml:lang="en">{\rtf1 case if that were the particular}</rdf:li></rdf:Alt></xmpDM:name></rdf:Description></rdf:li><rdf:li><rdf:Description xmpDM:startTime="234400" xmpDM:duration="3233" tscDM:valign="bottom" tscDM:halign="center" ><xmpDM:name><rdf:Alt><rdf:li xml:lang="en">{\rtf1 audience the test tube&apos;s would be would}</rdf:li></rdf:Alt></xmpDM:name></rdf:Description></rdf:li><rdf:li><rdf:Description xmpDM:startTime="237633" xmpDM:duration="1866" tscDM:valign="bottom" tscDM:halign="center" ><xmpDM:name><rdf:Alt><rdf:li xml:lang="en">{\rtf1 be the subject of the sentence and would}</rdf:li></rdf:Alt></xmpDM:name></rdf:Description></rdf:li><rdf:li><rdf:Description xmpDM:startTime="239500" xmpDM:duration="2066" tscDM:valign="bottom" tscDM:halign="center" ><xmpDM:name><rdf:Alt><rdf:li xml:lang="en">{\rtf1 it would make more sense to choose}</rdf:li></rdf:Alt></xmpDM:name></rdf:Description></rdf:li><rdf:li><rdf:Description xmpDM:startTime="241566" xmpDM:duration="2900" tscDM:valign="bottom" tscDM:halign="center" ><xmpDM:name><rdf:Alt><rdf:li xml:lang="en">{\rtf1 passive voice right so I just want kind}</rdf:li></rdf:Alt></xmpDM:name></rdf:Description></rdf:li><rdf:li><rdf:Description xmpDM:startTime="244466" xmpDM:duration="1733" tscDM:valign="bottom" tscDM:halign="center" ><xmpDM:name><rdf:Alt><rdf:li xml:lang="en">{\rtf1 of want to show you we&apos;re moving from}</rdf:li></rdf:Alt></xmpDM:name></rdf:Description></rdf:li><rdf:li><rdf:Description xmpDM:startTime="246200" xmpDM:duration="3466" tscDM:valign="bottom" tscDM:halign="center" ><xmpDM:name><rdf:Alt><rdf:li xml:lang="en">{\rtf1 changing words to now making making}</rdf:li></rdf:Alt></xmpDM:name></rdf:Description></rdf:li><rdf:li><rdf:Description xmpDM:startTime="249666" xmpDM:duration="2166" tscDM:valign="bottom" tscDM:halign="center" ><xmpDM:name><rdf:Alt><rdf:li xml:lang="en">{\rtf1 judgments about particular sentences}</rdf:li></rdf:Alt></xmpDM:name></rdf:Description></rdf:li><rdf:li><rdf:Description xmpDM:startTime="251833" xmpDM:duration="1333" tscDM:valign="bottom" tscDM:halign="center" ><xmpDM:name><rdf:Alt><rdf:li xml:lang="en">{\rtf1 right so we&apos;re moving along the}</rdf:li></rdf:Alt></xmpDM:name></rdf:Description></rdf:li><rdf:li><rdf:Description xmpDM:startTime="253166" xmpDM:duration="1600" tscDM:valign="bottom" tscDM:halign="center" ><xmpDM:name><rdf:Alt><rdf:li xml:lang="en">{\rtf1 continuum if you can imagine that your}</rdf:li></rdf:Alt></xmpDM:name></rdf:Description></rdf:li><rdf:li><rdf:Description xmpDM:startTime="254766" xmpDM:duration="2933" tscDM:valign="bottom" tscDM:halign="center" ><xmpDM:name><rdf:Alt><rdf:li xml:lang="en">{\rtf1 mind and that requires more editorial}</rdf:li></rdf:Alt></xmpDM:name></rdf:Description></rdf:li><rdf:li><rdf:Description xmpDM:startTime="257700" xmpDM:duration="3400" tscDM:valign="bottom" tscDM:halign="center" ><xmpDM:name><rdf:Alt><rdf:li xml:lang="en">{\rtf1 judgment so again active and passive one}</rdf:li></rdf:Alt></xmpDM:name></rdf:Description></rdf:li><rdf:li><rdf:Description xmpDM:startTime="261100" xmpDM:duration="2433" tscDM:valign="bottom" tscDM:halign="center" ><xmpDM:name><rdf:Alt><rdf:li xml:lang="en">{\rtf1 is not more correct than the other it&apos;s}</rdf:li></rdf:Alt></xmpDM:name></rdf:Description></rdf:li><rdf:li><rdf:Description xmpDM:startTime="263533" xmpDM:duration="1700" tscDM:valign="bottom" tscDM:halign="center" ><xmpDM:name><rdf:Alt><rdf:li xml:lang="en">{\rtf1 really as an editor}</rdf:li></rdf:Alt></xmpDM:name></rdf:Description></rdf:li><rdf:li><rdf:Description xmpDM:startTime="265233" xmpDM:duration="2500" tscDM:valign="bottom" tscDM:halign="center" ><xmpDM:name><rdf:Alt><rdf:li xml:lang="en">{\rtf1 determining how will I serve my reader}</rdf:li></rdf:Alt></xmpDM:name></rdf:Description></rdf:li><rdf:li><rdf:Description xmpDM:startTime="267733" xmpDM:duration="3066" tscDM:valign="bottom" tscDM:halign="center" ><xmpDM:name><rdf:Alt><rdf:li xml:lang="en">{\rtf1 most effectively should I reach}</rdf:li></rdf:Alt></xmpDM:name></rdf:Description></rdf:li><rdf:li><rdf:Description xmpDM:startTime="270800" xmpDM:duration="2366" tscDM:valign="bottom" tscDM:halign="center" ><xmpDM:name><rdf:Alt><rdf:li xml:lang="en">{\rtf1 restructure this particular sentence in}</rdf:li></rdf:Alt></xmpDM:name></rdf:Description></rdf:li><rdf:li><rdf:Description xmpDM:startTime="273166" xmpDM:duration="2833" tscDM:valign="bottom" tscDM:halign="center" ><xmpDM:name><rdf:Alt><rdf:li xml:lang="en">{\rtf1 an active voice or a passive voice way}</rdf:li></rdf:Alt></xmpDM:name></rdf:Description></rdf:li><rdf:li><rdf:Description xmpDM:startTime="276000" xmpDM:duration="4300" tscDM:valign="bottom" tscDM:halign="center" ><xmpDM:name><rdf:Alt><rdf:li xml:lang="en">{\rtf1 finally editing for tone so this is both}</rdf:li></rdf:Alt></xmpDM:name></rdf:Description></rdf:li><rdf:li><rdf:Description xmpDM:startTime="280300" xmpDM:duration="3200" tscDM:valign="bottom" tscDM:halign="center" ><xmpDM:name><rdf:Alt><rdf:li xml:lang="en">{\rtf1 at the word and the sentence level so if}</rdf:li></rdf:Alt></xmpDM:name></rdf:Description></rdf:li><rdf:li><rdf:Description xmpDM:startTime="283500" xmpDM:duration="2633" tscDM:valign="bottom" tscDM:halign="center" ><xmpDM:name><rdf:Alt><rdf:li xml:lang="en">{\rtf1 we if we take a direct statement in a}</rdf:li></rdf:Alt></xmpDM:name></rdf:Description></rdf:li><rdf:li><rdf:Description xmpDM:startTime="286133" xmpDM:duration="1500" tscDM:valign="bottom" tscDM:halign="center" ><xmpDM:name><rdf:Alt><rdf:li xml:lang="en">{\rtf1 piece of business communication for}</rdf:li></rdf:Alt></xmpDM:name></rdf:Description></rdf:li><rdf:li><rdf:Description xmpDM:startTime="287633" xmpDM:duration="4466" tscDM:valign="bottom" tscDM:halign="center" ><xmpDM:name><rdf:Alt><rdf:li xml:lang="en">{\rtf1 example to submit your report by Friday}</rdf:li></rdf:Alt></xmpDM:name></rdf:Description></rdf:li><rdf:li><rdf:Description xmpDM:startTime="292100" xmpDM:duration="4300" tscDM:valign="bottom" tscDM:halign="center" ><xmpDM:name><rdf:Alt><rdf:li xml:lang="en">{\rtf1 that actually can as we&apos;ll learn in the}</rdf:li></rdf:Alt></xmpDM:name></rdf:Description></rdf:li><rdf:li><rdf:Description xmpDM:startTime="296400" xmpDM:duration="2766" tscDM:valign="bottom" tscDM:halign="center" ><xmpDM:name><rdf:Alt><rdf:li xml:lang="en">{\rtf1 coming weeks of negatively impact the}</rdf:li></rdf:Alt></xmpDM:name></rdf:Description></rdf:li><rdf:li><rdf:Description xmpDM:startTime="299166" xmpDM:duration="1600" tscDM:valign="bottom" tscDM:halign="center" ><xmpDM:name><rdf:Alt><rdf:li xml:lang="en">{\rtf1 reader right it could turn off the}</rdf:li></rdf:Alt></xmpDM:name></rdf:Description></rdf:li><rdf:li><rdf:Description xmpDM:startTime="300766" xmpDM:duration="2300" tscDM:valign="bottom" tscDM:halign="center" ><xmpDM:name><rdf:Alt><rdf:li xml:lang="en">{\rtf1 reader because it threatens their}</rdf:li></rdf:Alt></xmpDM:name></rdf:Description></rdf:li><rdf:li><rdf:Description xmpDM:startTime="303066" xmpDM:duration="2833" tscDM:valign="bottom" tscDM:halign="center" ><xmpDM:name><rdf:Alt><rdf:li xml:lang="en">{\rtf1 autonomy you&apos;re telling them what to do}</rdf:li></rdf:Alt></xmpDM:name></rdf:Description></rdf:li><rdf:li><rdf:Description xmpDM:startTime="305900" xmpDM:duration="3500" tscDM:valign="bottom" tscDM:halign="center" ><xmpDM:name><rdf:Alt><rdf:li xml:lang="en">{\rtf1 and so as an editor we may suggest or we}</rdf:li></rdf:Alt></xmpDM:name></rdf:Description></rdf:li><rdf:li><rdf:Description xmpDM:startTime="309400" xmpDM:duration="3633" tscDM:valign="bottom" tscDM:halign="center" ><xmpDM:name><rdf:Alt><rdf:li xml:lang="en">{\rtf1 may revise this to a more indirect}</rdf:li></rdf:Alt></xmpDM:name></rdf:Description></rdf:li><rdf:li><rdf:Description xmpDM:startTime="313033" xmpDM:duration="3033" tscDM:valign="bottom" tscDM:halign="center" ><xmpDM:name><rdf:Alt><rdf:li xml:lang="en">{\rtf1 reading of this particular statement}</rdf:li></rdf:Alt></xmpDM:name></rdf:Description></rdf:li><rdf:li><rdf:Description xmpDM:startTime="316066" xmpDM:duration="2366" tscDM:valign="bottom" tscDM:halign="center" ><xmpDM:name><rdf:Alt><rdf:li xml:lang="en">{\rtf1 reports are due by Friday right so it&apos;s}</rdf:li></rdf:Alt></xmpDM:name></rdf:Description></rdf:li><rdf:li><rdf:Description xmpDM:startTime="318433" xmpDM:duration="3333" tscDM:valign="bottom" tscDM:halign="center" ><xmpDM:name><rdf:Alt><rdf:li xml:lang="en">{\rtf1 less accusatory it&apos;s less direct and}</rdf:li></rdf:Alt></xmpDM:name></rdf:Description></rdf:li><rdf:li><rdf:Description xmpDM:startTime="321766" xmpDM:duration="2400" tscDM:valign="bottom" tscDM:halign="center" ><xmpDM:name><rdf:Alt><rdf:li xml:lang="en">{\rtf1 it&apos;s more indirect and so if you imagine}</rdf:li></rdf:Alt></xmpDM:name></rdf:Description></rdf:li><rdf:li><rdf:Description xmpDM:startTime="324166" xmpDM:duration="2800" tscDM:valign="bottom" tscDM:halign="center" ><xmpDM:name><rdf:Alt><rdf:li xml:lang="en">{\rtf1 that continuum we&apos;re continuing to move}</rdf:li></rdf:Alt></xmpDM:name></rdf:Description></rdf:li><rdf:li><rdf:Description xmpDM:startTime="326966" xmpDM:duration="3366" tscDM:valign="bottom" tscDM:halign="center" ><xmpDM:name><rdf:Alt><rdf:li xml:lang="en">{\rtf1 toward more editorial judgment right}</rdf:li></rdf:Alt></xmpDM:name></rdf:Description></rdf:li><rdf:li><rdf:Description xmpDM:startTime="330333" xmpDM:duration="3333" tscDM:valign="bottom" tscDM:halign="center" ><xmpDM:name><rdf:Alt><rdf:li xml:lang="en">{\rtf1 again there&apos;s no more one correct way to}</rdf:li></rdf:Alt></xmpDM:name></rdf:Description></rdf:li><rdf:li><rdf:Description xmpDM:startTime="333666" xmpDM:duration="2533" tscDM:valign="bottom" tscDM:halign="center" ><xmpDM:name><rdf:Alt><rdf:li xml:lang="en">{\rtf1 dramatically correct way to write this}</rdf:li></rdf:Alt></xmpDM:name></rdf:Description></rdf:li><rdf:li><rdf:Description xmpDM:startTime="336200" xmpDM:duration="2466" tscDM:valign="bottom" tscDM:halign="center" ><xmpDM:name><rdf:Alt><rdf:li xml:lang="en">{\rtf1 particular phrase but now we&apos;re really}</rdf:li></rdf:Alt></xmpDM:name></rdf:Description></rdf:li><rdf:li><rdf:Description xmpDM:startTime="338666" xmpDM:duration="3100" tscDM:valign="bottom" tscDM:halign="center" ><xmpDM:name><rdf:Alt><rdf:li xml:lang="en">{\rtf1 thinking through the readers emotional}</rdf:li></rdf:Alt></xmpDM:name></rdf:Description></rdf:li><rdf:li><rdf:Description xmpDM:startTime="341766" xmpDM:duration="733" tscDM:valign="bottom" tscDM:halign="center" ><xmpDM:name><rdf:Alt><rdf:li xml:lang="en">{\rtf1 response}</rdf:li></rdf:Alt></xmpDM:name></rdf:Description></rdf:li><rdf:li><rdf:Description xmpDM:startTime="342500" xmpDM:duration="2300" tscDM:valign="bottom" tscDM:halign="center" ><xmpDM:name><rdf:Alt><rdf:li xml:lang="en">{\rtf1 how will the reader emotionally respond}</rdf:li></rdf:Alt></xmpDM:name></rdf:Description></rdf:li><rdf:li><rdf:Description xmpDM:startTime="344800" xmpDM:duration="3166" tscDM:valign="bottom" tscDM:halign="center" ><xmpDM:name><rdf:Alt><rdf:li xml:lang="en">{\rtf1 to this particular piece of writing}</rdf:li></rdf:Alt></xmpDM:name></rdf:Description></rdf:li><rdf:li><rdf:Description xmpDM:startTime="347966" xmpDM:duration="2200" tscDM:valign="bottom" tscDM:halign="center" ><xmpDM:name><rdf:Alt><rdf:li xml:lang="en">{\rtf1 those are some examples of style and}</rdf:li></rdf:Alt></xmpDM:name></rdf:Description></rdf:li><rdf:li><rdf:Description xmpDM:startTime="350166" xmpDM:duration="2866" tscDM:valign="bottom" tscDM:halign="center" ><xmpDM:name><rdf:Alt><rdf:li xml:lang="en">{\rtf1 tone editing I just wanted to give you}</rdf:li></rdf:Alt></xmpDM:name></rdf:Description></rdf:li><rdf:li><rdf:Description xmpDM:startTime="353033" xmpDM:duration="2033" tscDM:valign="bottom" tscDM:halign="center" ><xmpDM:name><rdf:Alt><rdf:li xml:lang="en">{\rtf1 one quick example of editing for}</rdf:li></rdf:Alt></xmpDM:name></rdf:Description></rdf:li><rdf:li><rdf:Description xmpDM:startTime="355066" xmpDM:duration="1433" tscDM:valign="bottom" tscDM:halign="center" ><xmpDM:name><rdf:Alt><rdf:li xml:lang="en">{\rtf1 organization again we&apos;re going to we&apos;re}</rdf:li></rdf:Alt></xmpDM:name></rdf:Description></rdf:li><rdf:li><rdf:Description xmpDM:startTime="356500" xmpDM:duration="2266" tscDM:valign="bottom" tscDM:halign="center" ><xmpDM:name><rdf:Alt><rdf:li xml:lang="en">{\rtf1 going to learn significantly more than}</rdf:li></rdf:Alt></xmpDM:name></rdf:Description></rdf:li><rdf:li><rdf:Description xmpDM:startTime="358766" xmpDM:duration="5200" tscDM:valign="bottom" tscDM:halign="center" ><xmpDM:name><rdf:Alt><rdf:li xml:lang="en">{\rtf1 just this one type of revision strategy}</rdf:li></rdf:Alt></xmpDM:name></rdf:Description></rdf:li><rdf:li><rdf:Description xmpDM:startTime="363966" xmpDM:duration="3166" tscDM:valign="bottom" tscDM:halign="center" ><xmpDM:name><rdf:Alt><rdf:li xml:lang="en">{\rtf1 but I wanted to walk you through one}</rdf:li></rdf:Alt></xmpDM:name></rdf:Description></rdf:li><rdf:li><rdf:Description xmpDM:startTime="367133" xmpDM:duration="3800" tscDM:valign="bottom" tscDM:halign="center" ><xmpDM:name><rdf:Alt><rdf:li xml:lang="en">{\rtf1 example okay so let&apos;s take a quick look}</rdf:li></rdf:Alt></xmpDM:name></rdf:Description></rdf:li><rdf:li><rdf:Description xmpDM:startTime="370933" xmpDM:duration="2366" tscDM:valign="bottom" tscDM:halign="center" ><xmpDM:name><rdf:Alt><rdf:li xml:lang="en">{\rtf1 at what we might do is editors when}</rdf:li></rdf:Alt></xmpDM:name></rdf:Description></rdf:li><rdf:li><rdf:Description xmpDM:startTime="373300" xmpDM:duration="1566" tscDM:valign="bottom" tscDM:halign="center" ><xmpDM:name><rdf:Alt><rdf:li xml:lang="en">{\rtf1 we&apos;re editing for organizations now}</rdf:li></rdf:Alt></xmpDM:name></rdf:Description></rdf:li><rdf:li><rdf:Description xmpDM:startTime="374866" xmpDM:duration="3900" tscDM:valign="bottom" tscDM:halign="center" ><xmpDM:name><rdf:Alt><rdf:li xml:lang="en">{\rtf1 we&apos;re really looking at documents as a}</rdf:li></rdf:Alt></xmpDM:name></rdf:Description></rdf:li><rdf:li><rdf:Description xmpDM:startTime="378766" xmpDM:duration="1633" tscDM:valign="bottom" tscDM:halign="center" ><xmpDM:name><rdf:Alt><rdf:li xml:lang="en">{\rtf1 whole and we&apos;re looking less at}</rdf:li></rdf:Alt></xmpDM:name></rdf:Description></rdf:li><rdf:li><rdf:Description xmpDM:startTime="380400" xmpDM:duration="2400" tscDM:valign="bottom" tscDM:halign="center" ><xmpDM:name><rdf:Alt><rdf:li xml:lang="en">{\rtf1 individual sentences or individual words}</rdf:li></rdf:Alt></xmpDM:name></rdf:Description></rdf:li><rdf:li><rdf:Description xmpDM:startTime="382800" xmpDM:duration="2500" tscDM:valign="bottom" tscDM:halign="center" ><xmpDM:name><rdf:Alt><rdf:li xml:lang="en">{\rtf1 so one thing that we might edit for is}</rdf:li></rdf:Alt></xmpDM:name></rdf:Description></rdf:li><rdf:li><rdf:Description xmpDM:startTime="385300" xmpDM:duration="2133" tscDM:valign="bottom" tscDM:halign="center" ><xmpDM:name><rdf:Alt><rdf:li xml:lang="en">{\rtf1 placement of the bottom line right so}</rdf:li></rdf:Alt></xmpDM:name></rdf:Description></rdf:li><rdf:li><rdf:Description xmpDM:startTime="387433" xmpDM:duration="2466" tscDM:valign="bottom" tscDM:halign="center" ><xmpDM:name><rdf:Alt><rdf:li xml:lang="en">{\rtf1 what is the main point that we&apos;re trying}</rdf:li></rdf:Alt></xmpDM:name></rdf:Description></rdf:li><rdf:li><rdf:Description xmpDM:startTime="389900" xmpDM:duration="5333" tscDM:valign="bottom" tscDM:halign="center" ><xmpDM:name><rdf:Alt><rdf:li xml:lang="en">{\rtf1 to communicate here as as a writer what}</rdf:li></rdf:Alt></xmpDM:name></rdf:Description></rdf:li><rdf:li><rdf:Description xmpDM:startTime="395233" xmpDM:duration="2166" tscDM:valign="bottom" tscDM:halign="center" ><xmpDM:name><rdf:Alt><rdf:li xml:lang="en">{\rtf1 is their main point so let&apos;s take a look}</rdf:li></rdf:Alt></xmpDM:name></rdf:Description></rdf:li><rdf:li><rdf:Description xmpDM:startTime="397400" xmpDM:duration="1200" tscDM:valign="bottom" tscDM:halign="center" ><xmpDM:name><rdf:Alt><rdf:li xml:lang="en">{\rtf1 at two examples so}</rdf:li></rdf:Alt></xmpDM:name></rdf:Description></rdf:li><rdf:li><rdf:Description xmpDM:startTime="398600" xmpDM:duration="2966" tscDM:valign="bottom" tscDM:halign="center" ><xmpDM:name><rdf:Alt><rdf:li xml:lang="en">{\rtf1 one says as we prepare a strategy}</rdf:li></rdf:Alt></xmpDM:name></rdf:Description></rdf:li><rdf:li><rdf:Description xmpDM:startTime="401566" xmpDM:duration="1900" tscDM:valign="bottom" tscDM:halign="center" ><xmpDM:name><rdf:Alt><rdf:li xml:lang="en">{\rtf1 proposal for central our team faces}</rdf:li></rdf:Alt></xmpDM:name></rdf:Description></rdf:li><rdf:li><rdf:Description xmpDM:startTime="403466" xmpDM:duration="2100" tscDM:valign="bottom" tscDM:halign="center" ><xmpDM:name><rdf:Alt><rdf:li xml:lang="en">{\rtf1 numerous challenges the most serious}</rdf:li></rdf:Alt></xmpDM:name></rdf:Description></rdf:li><rdf:li><rdf:Description xmpDM:startTime="405566" xmpDM:duration="1400" tscDM:valign="bottom" tscDM:halign="center" ><xmpDM:name><rdf:Alt><rdf:li xml:lang="en">{\rtf1 challenges involve apparent lack of}</rdf:li></rdf:Alt></xmpDM:name></rdf:Description></rdf:li><rdf:li><rdf:Description xmpDM:startTime="406966" xmpDM:duration="1633" tscDM:valign="bottom" tscDM:halign="center" ><xmpDM:name><rdf:Alt><rdf:li xml:lang="en">{\rtf1 communication from individual members}</rdf:li></rdf:Alt></xmpDM:name></rdf:Description></rdf:li><rdf:li><rdf:Description xmpDM:startTime="408600" xmpDM:duration="2533" tscDM:valign="bottom" tscDM:halign="center" ><xmpDM:name><rdf:Alt><rdf:li xml:lang="en">{\rtf1 and lack of knowledge about current}</rdf:li></rdf:Alt></xmpDM:name></rdf:Description></rdf:li><rdf:li><rdf:Description xmpDM:startTime="411133" xmpDM:duration="3133" tscDM:valign="bottom" tscDM:halign="center" ><xmpDM:name><rdf:Alt><rdf:li xml:lang="en">{\rtf1 centric processes then it goes to follow}</rdf:li></rdf:Alt></xmpDM:name></rdf:Description></rdf:li><rdf:li><rdf:Description xmpDM:startTime="414266" xmpDM:duration="2366" tscDM:valign="bottom" tscDM:halign="center" ><xmpDM:name><rdf:Alt><rdf:li xml:lang="en">{\rtf1 with some details one paragraph about}</rdf:li></rdf:Alt></xmpDM:name></rdf:Description></rdf:li><rdf:li><rdf:Description xmpDM:startTime="416633" xmpDM:duration="1400" tscDM:valign="bottom" tscDM:halign="center" ><xmpDM:name><rdf:Alt><rdf:li xml:lang="en">{\rtf1 mixed meetings two paragraphs about}</rdf:li></rdf:Alt></xmpDM:name></rdf:Description></rdf:li><rdf:li><rdf:Description xmpDM:startTime="418033" xmpDM:duration="3100" tscDM:valign="bottom" tscDM:halign="center" ><xmpDM:name><rdf:Alt><rdf:li xml:lang="en">{\rtf1 meeting participation and then a bit}</rdf:li></rdf:Alt></xmpDM:name></rdf:Description></rdf:li><rdf:li><rdf:Description xmpDM:startTime="421133" xmpDM:duration="2966" tscDM:valign="bottom" tscDM:halign="center" ><xmpDM:name><rdf:Alt><rdf:li xml:lang="en">{\rtf1 about knowledge of central processes and}</rdf:li></rdf:Alt></xmpDM:name></rdf:Description></rdf:li><rdf:li><rdf:Description xmpDM:startTime="424100" xmpDM:duration="2233" tscDM:valign="bottom" tscDM:halign="center" ><xmpDM:name><rdf:Alt><rdf:li xml:lang="en">{\rtf1 so in this case the bottom line really}</rdf:li></rdf:Alt></xmpDM:name></rdf:Description></rdf:li><rdf:li><rdf:Description xmpDM:startTime="426333" xmpDM:duration="2400" tscDM:valign="bottom" tscDM:halign="center" ><xmpDM:name><rdf:Alt><rdf:li xml:lang="en">{\rtf1 is that second sentence the most serious}</rdf:li></rdf:Alt></xmpDM:name></rdf:Description></rdf:li><rdf:li><rdf:Description xmpDM:startTime="428733" xmpDM:duration="1433" tscDM:valign="bottom" tscDM:halign="center" ><xmpDM:name><rdf:Alt><rdf:li xml:lang="en">{\rtf1 challenges involve apparent lack of}</rdf:li></rdf:Alt></xmpDM:name></rdf:Description></rdf:li><rdf:li><rdf:Description xmpDM:startTime="430166" xmpDM:duration="3400" tscDM:valign="bottom" tscDM:halign="center" ><xmpDM:name><rdf:Alt><rdf:li xml:lang="en">{\rtf1 commitment and lack of knowledge right}</rdf:li></rdf:Alt></xmpDM:name></rdf:Description></rdf:li><rdf:li><rdf:Description xmpDM:startTime="433566" xmpDM:duration="1233" tscDM:valign="bottom" tscDM:halign="center" ><xmpDM:name><rdf:Alt><rdf:li xml:lang="en">{\rtf1 so really what this piece of}</rdf:li></rdf:Alt></xmpDM:name></rdf:Description></rdf:li><rdf:li><rdf:Description xmpDM:startTime="434800" xmpDM:duration="1766" tscDM:valign="bottom" tscDM:halign="center" ><xmpDM:name><rdf:Alt><rdf:li xml:lang="en">{\rtf1 communication is trying to get across is}</rdf:li></rdf:Alt></xmpDM:name></rdf:Description></rdf:li><rdf:li><rdf:Description xmpDM:startTime="436566" xmpDM:duration="3000" tscDM:valign="bottom" tscDM:halign="center" ><xmpDM:name><rdf:Alt><rdf:li xml:lang="en">{\rtf1 we need you to be more committed and so}</rdf:li></rdf:Alt></xmpDM:name></rdf:Description></rdf:li><rdf:li><rdf:Description xmpDM:startTime="439566" xmpDM:duration="1766" tscDM:valign="bottom" tscDM:halign="center" ><xmpDM:name><rdf:Alt><rdf:li xml:lang="en">{\rtf1 this is an example of what&apos;s called}</rdf:li></rdf:Alt></xmpDM:name></rdf:Description></rdf:li><rdf:li><rdf:Description xmpDM:startTime="441333" xmpDM:duration="3200" tscDM:valign="bottom" tscDM:halign="center" ><xmpDM:name><rdf:Alt><rdf:li xml:lang="en">{\rtf1 direct or deductive organizational}</rdf:li></rdf:Alt></xmpDM:name></rdf:Description></rdf:li><rdf:li><rdf:Description xmpDM:startTime="444533" xmpDM:duration="1933" tscDM:valign="bottom" tscDM:halign="center" ><xmpDM:name><rdf:Alt><rdf:li xml:lang="en">{\rtf1 strategy where you put them the main}</rdf:li></rdf:Alt></xmpDM:name></rdf:Description></rdf:li><rdf:li><rdf:Description xmpDM:startTime="446466" xmpDM:duration="3866" tscDM:valign="bottom" tscDM:halign="center" ><xmpDM:name><rdf:Alt><rdf:li xml:lang="en">{\rtf1 idea in the in the beginning you fall}</rdf:li></rdf:Alt></xmpDM:name></rdf:Description></rdf:li><rdf:li><rdf:Description xmpDM:startTime="450333" xmpDM:duration="1900" tscDM:valign="bottom" tscDM:halign="center" ><xmpDM:name><rdf:Alt><rdf:li xml:lang="en">{\rtf1 around it and then you and then what}</rdf:li></rdf:Alt></xmpDM:name></rdf:Description></rdf:li><rdf:li><rdf:Description xmpDM:startTime="452233" xmpDM:duration="4766" tscDM:valign="bottom" tscDM:halign="center" ><xmpDM:name><rdf:Alt><rdf:li xml:lang="en">{\rtf1 follows is a bit of extra detail about}</rdf:li></rdf:Alt></xmpDM:name></rdf:Description></rdf:li><rdf:li><rdf:Description xmpDM:startTime="457000" xmpDM:duration="2633" tscDM:valign="bottom" tscDM:halign="center" ><xmpDM:name><rdf:Alt><rdf:li xml:lang="en">{\rtf1 that main idea and we can see that this}</rdf:li></rdf:Alt></xmpDM:name></rdf:Description></rdf:li><rdf:li><rdf:Description xmpDM:startTime="459633" xmpDM:duration="1733" tscDM:valign="bottom" tscDM:halign="center" ><xmpDM:name><rdf:Alt><rdf:li xml:lang="en">{\rtf1 would be effective in particular}</rdf:li></rdf:Alt></xmpDM:name></rdf:Description></rdf:li><rdf:li><rdf:Description xmpDM:startTime="461366" xmpDM:duration="2533" tscDM:valign="bottom" tscDM:halign="center" ><xmpDM:name><rdf:Alt><rdf:li xml:lang="en">{\rtf1 contexts or situations but as editors we}</rdf:li></rdf:Alt></xmpDM:name></rdf:Description></rdf:li><rdf:li><rdf:Description xmpDM:startTime="463900" xmpDM:duration="2233" tscDM:valign="bottom" tscDM:halign="center" ><xmpDM:name><rdf:Alt><rdf:li xml:lang="en">{\rtf1 need to think who is our audience so if}</rdf:li></rdf:Alt></xmpDM:name></rdf:Description></rdf:li><rdf:li><rdf:Description xmpDM:startTime="466133" xmpDM:duration="2266" tscDM:valign="bottom" tscDM:halign="center" ><xmpDM:name><rdf:Alt><rdf:li xml:lang="en">{\rtf1 our audience is actual team members on}</rdf:li></rdf:Alt></xmpDM:name></rdf:Description></rdf:li><rdf:li><rdf:Description xmpDM:startTime="468400" xmpDM:duration="3966" tscDM:valign="bottom" tscDM:halign="center" ><xmpDM:name><rdf:Alt><rdf:li xml:lang="en">{\rtf1 this team it would it would it would}</rdf:li></rdf:Alt></xmpDM:name></rdf:Description></rdf:li><rdf:li><rdf:Description xmpDM:startTime="472366" xmpDM:duration="2900" tscDM:valign="bottom" tscDM:halign="center" ><xmpDM:name><rdf:Alt><rdf:li xml:lang="en">{\rtf1 probably be offensive to particular team}</rdf:li></rdf:Alt></xmpDM:name></rdf:Description></rdf:li><rdf:li><rdf:Description xmpDM:startTime="475266" xmpDM:duration="1333" tscDM:valign="bottom" tscDM:halign="center" ><xmpDM:name><rdf:Alt><rdf:li xml:lang="en">{\rtf1 members they might feel like they&apos;re}</rdf:li></rdf:Alt></xmpDM:name></rdf:Description></rdf:li><rdf:li><rdf:Description xmpDM:startTime="476600" xmpDM:duration="1433" tscDM:valign="bottom" tscDM:halign="center" ><xmpDM:name><rdf:Alt><rdf:li xml:lang="en">{\rtf1 being called out they might feel like}</rdf:li></rdf:Alt></xmpDM:name></rdf:Description></rdf:li><rdf:li><rdf:Description xmpDM:startTime="478033" xmpDM:duration="4166" tscDM:valign="bottom" tscDM:halign="center" ><xmpDM:name><rdf:Alt><rdf:li xml:lang="en">{\rtf1 they&apos;re being embarrassed in front of}</rdf:li></rdf:Alt></xmpDM:name></rdf:Description></rdf:li><rdf:li><rdf:Description xmpDM:startTime="482200" xmpDM:duration="3233" tscDM:valign="bottom" tscDM:halign="center" ><xmpDM:name><rdf:Alt><rdf:li xml:lang="en">{\rtf1 other team members and so we can we can}</rdf:li></rdf:Alt></xmpDM:name></rdf:Description></rdf:li><rdf:li><rdf:Description xmpDM:startTime="485433" xmpDM:duration="2600" tscDM:valign="bottom" tscDM:halign="center" ><xmpDM:name><rdf:Alt><rdf:li xml:lang="en">{\rtf1 actually communicate this or revive this}</rdf:li></rdf:Alt></xmpDM:name></rdf:Description></rdf:li><rdf:li><rdf:Description xmpDM:startTime="488033" xmpDM:duration="5733" tscDM:valign="bottom" tscDM:halign="center" ><xmpDM:name><rdf:Alt><rdf:li xml:lang="en">{\rtf1 as editors to a more indirect strategy}</rdf:li></rdf:Alt></xmpDM:name></rdf:Description></rdf:li><rdf:li><rdf:Description xmpDM:startTime="493766" xmpDM:duration="4566" tscDM:valign="bottom" tscDM:halign="center" ><xmpDM:name><rdf:Alt><rdf:li xml:lang="en">{\rtf1 for that particular audience so if we&apos;re}</rdf:li></rdf:Alt></xmpDM:name></rdf:Description></rdf:li><rdf:li><rdf:Description xmpDM:startTime="498333" xmpDM:duration="3800" tscDM:valign="bottom" tscDM:halign="center" ><xmpDM:name><rdf:Alt><rdf:li xml:lang="en">{\rtf1 to look at a revised version of this we}</rdf:li></rdf:Alt></xmpDM:name></rdf:Description></rdf:li><rdf:li><rdf:Description xmpDM:startTime="502133" xmpDM:duration="2300" tscDM:valign="bottom" tscDM:halign="center" ><xmpDM:name><rdf:Alt><rdf:li xml:lang="en">{\rtf1 might it might look something like this}</rdf:li></rdf:Alt></xmpDM:name></rdf:Description></rdf:li><rdf:li><rdf:Description xmpDM:startTime="504433" xmpDM:duration="2066" tscDM:valign="bottom" tscDM:halign="center" ><xmpDM:name><rdf:Alt><rdf:li xml:lang="en">{\rtf1 as we prepare a strategy proposal for}</rdf:li></rdf:Alt></xmpDM:name></rdf:Description></rdf:li><rdf:li><rdf:Description xmpDM:startTime="506500" xmpDM:duration="1300" tscDM:valign="bottom" tscDM:halign="center" ><xmpDM:name><rdf:Alt><rdf:li xml:lang="en">{\rtf1 centra our team faces numerous}</rdf:li></rdf:Alt></xmpDM:name></rdf:Description></rdf:li><rdf:li><rdf:Description xmpDM:startTime="507800" xmpDM:duration="2633" tscDM:valign="bottom" tscDM:halign="center" ><xmpDM:name><rdf:Alt><rdf:li xml:lang="en">{\rtf1 challenges and then some detail about}</rdf:li></rdf:Alt></xmpDM:name></rdf:Description></rdf:li><rdf:li><rdf:Description xmpDM:startTime="510433" xmpDM:duration="1900" tscDM:valign="bottom" tscDM:halign="center" ><xmpDM:name><rdf:Alt><rdf:li xml:lang="en">{\rtf1 knowledge of central processes so}</rdf:li></rdf:Alt></xmpDM:name></rdf:Description></rdf:li><rdf:li><rdf:Description xmpDM:startTime="512333" xmpDM:duration="2000" tscDM:valign="bottom" tscDM:halign="center" ><xmpDM:name><rdf:Alt><rdf:li xml:lang="en">{\rtf1 starting sort of more general and less}</rdf:li></rdf:Alt></xmpDM:name></rdf:Description></rdf:li><rdf:li><rdf:Description xmpDM:startTime="514333" xmpDM:duration="2833" tscDM:valign="bottom" tscDM:halign="center" ><xmpDM:name><rdf:Alt><rdf:li xml:lang="en">{\rtf1 direct toward the particular team}</rdf:li></rdf:Alt></xmpDM:name></rdf:Description></rdf:li><rdf:li><rdf:Description xmpDM:startTime="517166" xmpDM:duration="1833" tscDM:valign="bottom" tscDM:halign="center" ><xmpDM:name><rdf:Alt><rdf:li xml:lang="en">{\rtf1 members and then some detail about}</rdf:li></rdf:Alt></xmpDM:name></rdf:Description></rdf:li><rdf:li><rdf:Description xmpDM:startTime="519000" xmpDM:duration="1133" tscDM:valign="bottom" tscDM:halign="center" ><xmpDM:name><rdf:Alt><rdf:li xml:lang="en">{\rtf1 missed meetings and meeting}</rdf:li></rdf:Alt></xmpDM:name></rdf:Description></rdf:li><rdf:li><rdf:Description xmpDM:startTime="520133" xmpDM:duration="1933" tscDM:valign="bottom" tscDM:halign="center" ><xmpDM:name><rdf:Alt><rdf:li xml:lang="en">{\rtf1 participation and then the bottom line}</rdf:li></rdf:Alt></xmpDM:name></rdf:Description></rdf:li><rdf:li><rdf:Description xmpDM:startTime="522066" xmpDM:duration="2366" tscDM:valign="bottom" tscDM:halign="center" ><xmpDM:name><rdf:Alt><rdf:li xml:lang="en">{\rtf1 at the end to summarize our team&apos;s most}</rdf:li></rdf:Alt></xmpDM:name></rdf:Description></rdf:li><rdf:li><rdf:Description xmpDM:startTime="524433" xmpDM:duration="1533" tscDM:valign="bottom" tscDM:halign="center" ><xmpDM:name><rdf:Alt><rdf:li xml:lang="en">{\rtf1 serious challenges involve lack of}</rdf:li></rdf:Alt></xmpDM:name></rdf:Description></rdf:li><rdf:li><rdf:Description xmpDM:startTime="525966" xmpDM:duration="1266" tscDM:valign="bottom" tscDM:halign="center" ><xmpDM:name><rdf:Alt><rdf:li xml:lang="en">{\rtf1 knowledge about current central}</rdf:li></rdf:Alt></xmpDM:name></rdf:Description></rdf:li><rdf:li><rdf:Description xmpDM:startTime="527233" xmpDM:duration="1866" tscDM:valign="bottom" tscDM:halign="center" ><xmpDM:name><rdf:Alt><rdf:li xml:lang="en">{\rtf1 processes and apparent lack of}</rdf:li></rdf:Alt></xmpDM:name></rdf:Description></rdf:li><rdf:li><rdf:Description xmpDM:startTime="529100" xmpDM:duration="1866" tscDM:valign="bottom" tscDM:halign="center" ><xmpDM:name><rdf:Alt><rdf:li xml:lang="en">{\rtf1 commitment from individual members}</rdf:li></rdf:Alt></xmpDM:name></rdf:Description></rdf:li><rdf:li><rdf:Description xmpDM:startTime="530966" xmpDM:duration="3266" tscDM:valign="bottom" tscDM:halign="center" ><xmpDM:name><rdf:Alt><rdf:li xml:lang="en">{\rtf1 right so we&apos;re we&apos;re just softening the}</rdf:li></rdf:Alt></xmpDM:name></rdf:Description></rdf:li><rdf:li><rdf:Description xmpDM:startTime="534233" xmpDM:duration="4366" tscDM:valign="bottom" tscDM:halign="center" ><xmpDM:name><rdf:Alt><rdf:li xml:lang="en">{\rtf1 blow a little bit here as editors and so}</rdf:li></rdf:Alt></xmpDM:name></rdf:Description></rdf:li><rdf:li><rdf:Description xmpDM:startTime="538600" xmpDM:duration="2800" tscDM:valign="bottom" tscDM:halign="center" ><xmpDM:name><rdf:Alt><rdf:li xml:lang="en">{\rtf1 again the idea is just to introduce you}</rdf:li></rdf:Alt></xmpDM:name></rdf:Description></rdf:li><rdf:li><rdf:Description xmpDM:startTime="541400" xmpDM:duration="3700" tscDM:valign="bottom" tscDM:halign="center" ><xmpDM:name><rdf:Alt><rdf:li xml:lang="en">{\rtf1 to this idea of editing really takes}</rdf:li></rdf:Alt></xmpDM:name></rdf:Description></rdf:li><rdf:li><rdf:Description xmpDM:startTime="545100" xmpDM:duration="2466" tscDM:valign="bottom" tscDM:halign="center" ><xmpDM:name><rdf:Alt><rdf:li xml:lang="en">{\rtf1 some judgment and part of that judgment}</rdf:li></rdf:Alt></xmpDM:name></rdf:Description></rdf:li><rdf:li><rdf:Description xmpDM:startTime="547566" xmpDM:duration="2866" tscDM:valign="bottom" tscDM:halign="center" ><xmpDM:name><rdf:Alt><rdf:li xml:lang="en">{\rtf1 is understanding the entire document in}</rdf:li></rdf:Alt></xmpDM:name></rdf:Description></rdf:li><rdf:li><rdf:Description xmpDM:startTime="550433" xmpDM:duration="2066" tscDM:valign="bottom" tscDM:halign="center" ><xmpDM:name><rdf:Alt><rdf:li xml:lang="en">{\rtf1 the whole and really understanding the}</rdf:li></rdf:Alt></xmpDM:name></rdf:Description></rdf:li><rdf:li><rdf:Description xmpDM:startTime="552500" xmpDM:duration="3233" tscDM:valign="bottom" tscDM:halign="center" ><xmpDM:name><rdf:Alt><rdf:li xml:lang="en">{\rtf1 particular context and audience at which}</rdf:li></rdf:Alt></xmpDM:name></rdf:Description></rdf:li><rdf:li><rdf:Description xmpDM:startTime="555733" xmpDM:duration="4766" tscDM:valign="bottom" tscDM:halign="center" ><xmpDM:name><rdf:Alt><rdf:li xml:lang="en">{\rtf1 the the document is trying to meet we}</rdf:li></rdf:Alt></xmpDM:name></rdf:Description></rdf:li><rdf:li><rdf:Description xmpDM:startTime="560500" xmpDM:duration="2600" tscDM:valign="bottom" tscDM:halign="center" ><xmpDM:name><rdf:Alt><rdf:li xml:lang="en">{\rtf1 take a look at our continuum again I}</rdf:li></rdf:Alt></xmpDM:name></rdf:Description></rdf:li><rdf:li><rdf:Description xmpDM:startTime="563100" xmpDM:duration="2433" tscDM:valign="bottom" tscDM:halign="center" ><xmpDM:name><rdf:Alt><rdf:li xml:lang="en">{\rtf1 kind of walked you through from copy}</rdf:li></rdf:Alt></xmpDM:name></rdf:Description></rdf:li><rdf:li><rdf:Description xmpDM:startTime="565533" xmpDM:duration="1466" tscDM:valign="bottom" tscDM:halign="center" ><xmpDM:name><rdf:Alt><rdf:li xml:lang="en">{\rtf1 editing to style and tone to}</rdf:li></rdf:Alt></xmpDM:name></rdf:Description></rdf:li><rdf:li><rdf:Description xmpDM:startTime="567000" xmpDM:duration="2200" tscDM:valign="bottom" tscDM:halign="center" ><xmpDM:name><rdf:Alt><rdf:li xml:lang="en">{\rtf1 organization and then we&apos;re going to}</rdf:li></rdf:Alt></xmpDM:name></rdf:Description></rdf:li><rdf:li><rdf:Description xmpDM:startTime="569200" xmpDM:duration="3466" tscDM:valign="bottom" tscDM:halign="center" ><xmpDM:name><rdf:Alt><rdf:li xml:lang="en">{\rtf1 look at things like visual design we&apos;re}</rdf:li></rdf:Alt></xmpDM:name></rdf:Description></rdf:li><rdf:li><rdf:Description xmpDM:startTime="572666" xmpDM:duration="3900" tscDM:valign="bottom" tscDM:halign="center" ><xmpDM:name><rdf:Alt><rdf:li xml:lang="en">{\rtf1 going to look at things like cohesion}</rdf:li></rdf:Alt></xmpDM:name></rdf:Description></rdf:li><rdf:li><rdf:Description xmpDM:startTime="576566" xmpDM:duration="3066" tscDM:valign="bottom" tscDM:halign="center" ><xmpDM:name><rdf:Alt><rdf:li xml:lang="en">{\rtf1 but as we walk through you can kind of}</rdf:li></rdf:Alt></xmpDM:name></rdf:Description></rdf:li><rdf:li><rdf:Description xmpDM:startTime="579633" xmpDM:duration="3033" tscDM:valign="bottom" tscDM:halign="center" ><xmpDM:name><rdf:Alt><rdf:li xml:lang="en">{\rtf1 see it really takes more judgment as we}</rdf:li></rdf:Alt></xmpDM:name></rdf:Description></rdf:li><rdf:li><rdf:Description xmpDM:startTime="582666" xmpDM:duration="3966" tscDM:valign="bottom" tscDM:halign="center" ><xmpDM:name><rdf:Alt><rdf:li xml:lang="en">{\rtf1 move along and so part of what I want to}</rdf:li></rdf:Alt></xmpDM:name></rdf:Description></rdf:li><rdf:li><rdf:Description xmpDM:startTime="586633" xmpDM:duration="1666" tscDM:valign="bottom" tscDM:halign="center" ><xmpDM:name><rdf:Alt><rdf:li xml:lang="en">{\rtf1 teach and I want you to learn in this}</rdf:li></rdf:Alt></xmpDM:name></rdf:Description></rdf:li><rdf:li><rdf:Description xmpDM:startTime="588300" xmpDM:duration="2566" tscDM:valign="bottom" tscDM:halign="center" ><xmpDM:name><rdf:Alt><rdf:li xml:lang="en">{\rtf1 course is of course I want you to learn}</rdf:li></rdf:Alt></xmpDM:name></rdf:Description></rdf:li><rdf:li><rdf:Description xmpDM:startTime="590866" xmpDM:duration="2266" tscDM:valign="bottom" tscDM:halign="center" ><xmpDM:name><rdf:Alt><rdf:li xml:lang="en">{\rtf1 the rules how to dramatically make}</rdf:li></rdf:Alt></xmpDM:name></rdf:Description></rdf:li><rdf:li><rdf:Description xmpDM:startTime="593133" xmpDM:duration="2533" tscDM:valign="bottom" tscDM:halign="center" ><xmpDM:name><rdf:Alt><rdf:li xml:lang="en">{\rtf1 things more grammatical and also make}</rdf:li></rdf:Alt></xmpDM:name></rdf:Description></rdf:li><rdf:li><rdf:Description xmpDM:startTime="595666" xmpDM:duration="3966" tscDM:valign="bottom" tscDM:halign="center" ><xmpDM:name><rdf:Alt><rdf:li xml:lang="en">{\rtf1 things in appropriate style and tone for}</rdf:li></rdf:Alt></xmpDM:name></rdf:Description></rdf:li><rdf:li><rdf:Description xmpDM:startTime="599633" xmpDM:duration="3600" tscDM:valign="bottom" tscDM:halign="center" ><xmpDM:name><rdf:Alt><rdf:li xml:lang="en">{\rtf1 a particular reader but as we move along}</rdf:li></rdf:Alt></xmpDM:name></rdf:Description></rdf:li><rdf:li><rdf:Description xmpDM:startTime="603233" xmpDM:duration="3666" tscDM:valign="bottom" tscDM:halign="center" ><xmpDM:name><rdf:Alt><rdf:li xml:lang="en">{\rtf1 it&apos;s really about honing in on this}</rdf:li></rdf:Alt></xmpDM:name></rdf:Description></rdf:li><rdf:li><rdf:Description xmpDM:startTime="606900" xmpDM:duration="4100" tscDM:valign="bottom" tscDM:halign="center" ><xmpDM:name><rdf:Alt><rdf:li xml:lang="en">{\rtf1 holistic view of editing and so if we}</rdf:li></rdf:Alt></xmpDM:name></rdf:Description></rdf:li><rdf:li><rdf:Description xmpDM:startTime="611000" xmpDM:duration="2066" tscDM:valign="bottom" tscDM:halign="center" ><xmpDM:name><rdf:Alt><rdf:li xml:lang="en">{\rtf1 look at strategies for editing and we}</rdf:li></rdf:Alt></xmpDM:name></rdf:Description></rdf:li><rdf:li><rdf:Description xmpDM:startTime="613066" xmpDM:duration="3033" tscDM:valign="bottom" tscDM:halign="center" ><xmpDM:name><rdf:Alt><rdf:li xml:lang="en">{\rtf1 look at this pyramid the way it&apos;s being}</rdf:li></rdf:Alt></xmpDM:name></rdf:Description></rdf:li><rdf:li><rdf:Description xmpDM:startTime="616100" xmpDM:duration="3766" tscDM:valign="bottom" tscDM:halign="center" ><xmpDM:name><rdf:Alt><rdf:li xml:lang="en">{\rtf1 taught is actually I&apos;m actually starting}</rdf:li></rdf:Alt></xmpDM:name></rdf:Description></rdf:li><rdf:li><rdf:Description xmpDM:startTime="619866" xmpDM:duration="2000" tscDM:valign="bottom" tscDM:halign="center" ><xmpDM:name><rdf:Alt><rdf:li xml:lang="en">{\rtf1 at the top and moving to the bottom but}</rdf:li></rdf:Alt></xmpDM:name></rdf:Description></rdf:li><rdf:li><rdf:Description xmpDM:startTime="621866" xmpDM:duration="2633" tscDM:valign="bottom" tscDM:halign="center" ><xmpDM:name><rdf:Alt><rdf:li xml:lang="en">{\rtf1 as you are editing and we&apos;ll talk more}</rdf:li></rdf:Alt></xmpDM:name></rdf:Description></rdf:li><rdf:li><rdf:Description xmpDM:startTime="624500" xmpDM:duration="2500" tscDM:valign="bottom" tscDM:halign="center" ><xmpDM:name><rdf:Alt><rdf:li xml:lang="en">{\rtf1 about how to do this specific strategies}</rdf:li></rdf:Alt></xmpDM:name></rdf:Description></rdf:li><rdf:li><rdf:Description xmpDM:startTime="627000" xmpDM:duration="2433" tscDM:valign="bottom" tscDM:halign="center" ><xmpDM:name><rdf:Alt><rdf:li xml:lang="en">{\rtf1 and how to do this it&apos;s actually better}</rdf:li></rdf:Alt></xmpDM:name></rdf:Description></rdf:li><rdf:li><rdf:Description xmpDM:startTime="629433" xmpDM:duration="2466" tscDM:valign="bottom" tscDM:halign="center" ><xmpDM:name><rdf:Alt><rdf:li xml:lang="en">{\rtf1 to start at the bottom so to read a}</rdf:li></rdf:Alt></xmpDM:name></rdf:Description></rdf:li><rdf:li><rdf:Description xmpDM:startTime="631900" xmpDM:duration="2333" tscDM:valign="bottom" tscDM:halign="center" ><xmpDM:name><rdf:Alt><rdf:li xml:lang="en">{\rtf1 document as a whole and then sort of}</rdf:li></rdf:Alt></xmpDM:name></rdf:Description></rdf:li><rdf:li><rdf:Description xmpDM:startTime="634233" xmpDM:duration="3666" tscDM:valign="bottom" tscDM:halign="center" ><xmpDM:name><rdf:Alt><rdf:li xml:lang="en">{\rtf1 move toward the left of that continuum}</rdf:li></rdf:Alt></xmpDM:name></rdf:Description></rdf:li><rdf:li><rdf:Description xmpDM:startTime="637900" xmpDM:duration="3966" tscDM:valign="bottom" tscDM:halign="center" ><xmpDM:name><rdf:Alt><rdf:li xml:lang="en">{\rtf1 right so really sort of a couple reasons}</rdf:li></rdf:Alt></xmpDM:name></rdf:Description></rdf:li><rdf:li><rdf:Description xmpDM:startTime="641866" xmpDM:duration="2000" tscDM:valign="bottom" tscDM:halign="center" ><xmpDM:name><rdf:Alt><rdf:li xml:lang="en">{\rtf1 for this but the most pragmatic reason}</rdf:li></rdf:Alt></xmpDM:name></rdf:Description></rdf:li><rdf:li><rdf:Description xmpDM:startTime="643866" xmpDM:duration="2600" tscDM:valign="bottom" tscDM:halign="center" ><xmpDM:name><rdf:Alt><rdf:li xml:lang="en">{\rtf1 for this is let&apos;s say you&apos;ve copy edited}</rdf:li></rdf:Alt></xmpDM:name></rdf:Description></rdf:li><rdf:li><rdf:Description xmpDM:startTime="646466" xmpDM:duration="2533" tscDM:valign="bottom" tscDM:halign="center" ><xmpDM:name><rdf:Alt><rdf:li xml:lang="en">{\rtf1 this document and it&apos;s perfect and}</rdf:li></rdf:Alt></xmpDM:name></rdf:Description></rdf:li><rdf:li><rdf:Description xmpDM:startTime="649000" xmpDM:duration="2433" tscDM:valign="bottom" tscDM:halign="center" ><xmpDM:name><rdf:Alt><rdf:li xml:lang="en">{\rtf1 grammatically correct the problem with}</rdf:li></rdf:Alt></xmpDM:name></rdf:Description></rdf:li><rdf:li><rdf:Description xmpDM:startTime="651433" xmpDM:duration="2900" tscDM:valign="bottom" tscDM:halign="center" ><xmpDM:name><rdf:Alt><rdf:li xml:lang="en">{\rtf1 that is if you then move on to}</rdf:li></rdf:Alt></xmpDM:name></rdf:Description></rdf:li><rdf:li><rdf:Description xmpDM:startTime="654333" xmpDM:duration="2333" tscDM:valign="bottom" tscDM:halign="center" ><xmpDM:name><rdf:Alt><rdf:li xml:lang="en">{\rtf1 comprehensive editing after that you}</rdf:li></rdf:Alt></xmpDM:name></rdf:Description></rdf:li><rdf:li><rdf:Description xmpDM:startTime="656666" xmpDM:duration="2866" tscDM:valign="bottom" tscDM:halign="center" ><xmpDM:name><rdf:Alt><rdf:li xml:lang="en">{\rtf1 might just remove entire chunks or}</rdf:li></rdf:Alt></xmpDM:name></rdf:Description></rdf:li><rdf:li><rdf:Description xmpDM:startTime="659533" xmpDM:duration="1533" tscDM:valign="bottom" tscDM:halign="center" ><xmpDM:name><rdf:Alt><rdf:li xml:lang="en">{\rtf1 sections of text that you&apos;ve already}</rdf:li></rdf:Alt></xmpDM:name></rdf:Description></rdf:li><rdf:li><rdf:Description xmpDM:startTime="661066" xmpDM:duration="1666" tscDM:valign="bottom" tscDM:halign="center" ><xmpDM:name><rdf:Alt><rdf:li xml:lang="en">{\rtf1 edited so you&apos;ve kind of wasted time}</rdf:li></rdf:Alt></xmpDM:name></rdf:Description></rdf:li><rdf:li><rdf:Description xmpDM:startTime="662733" xmpDM:duration="1966" tscDM:valign="bottom" tscDM:halign="center" ><xmpDM:name><rdf:Alt><rdf:li xml:lang="en">{\rtf1 copy editing}</rdf:li></rdf:Alt></xmpDM:name></rdf:Description></rdf:li><rdf:li><rdf:Description xmpDM:startTime="664700" xmpDM:duration="2666" tscDM:valign="bottom" tscDM:halign="center" ><xmpDM:name><rdf:Alt><rdf:li xml:lang="en">{\rtf1 and so we&apos;ll talk about this more but}</rdf:li></rdf:Alt></xmpDM:name></rdf:Description></rdf:li><rdf:li><rdf:Description xmpDM:startTime="667366" xmpDM:duration="2333" tscDM:valign="bottom" tscDM:halign="center" ><xmpDM:name><rdf:Alt><rdf:li xml:lang="en">{\rtf1 really as an editor the first thing that}</rdf:li></rdf:Alt></xmpDM:name></rdf:Description></rdf:li><rdf:li><rdf:Description xmpDM:startTime="669700" xmpDM:duration="2366" tscDM:valign="bottom" tscDM:halign="center" ><xmpDM:name><rdf:Alt><rdf:li xml:lang="en">{\rtf1 we&apos;re going to do is to read an entire}</rdf:li></rdf:Alt></xmpDM:name></rdf:Description></rdf:li><rdf:li><rdf:Description xmpDM:startTime="672066" xmpDM:duration="3466" tscDM:valign="bottom" tscDM:halign="center" ><xmpDM:name><rdf:Alt><rdf:li xml:lang="en">{\rtf1 document and and and really think}</rdf:li></rdf:Alt></xmpDM:name></rdf:Description></rdf:li><rdf:li><rdf:Description xmpDM:startTime="675533" xmpDM:duration="1766" tscDM:valign="bottom" tscDM:halign="center" ><xmpDM:name><rdf:Alt><rdf:li xml:lang="en">{\rtf1 through who is our audience who is our}</rdf:li></rdf:Alt></xmpDM:name></rdf:Description></rdf:li><rdf:li><rdf:Description xmpDM:startTime="677300" xmpDM:duration="1633" tscDM:valign="bottom" tscDM:halign="center" ><xmpDM:name><rdf:Alt><rdf:li xml:lang="en">{\rtf1 content what is our context what is the}</rdf:li></rdf:Alt></xmpDM:name></rdf:Description></rdf:li><rdf:li><rdf:Description xmpDM:startTime="678933" xmpDM:duration="2166" tscDM:valign="bottom" tscDM:halign="center" ><xmpDM:name><rdf:Alt><rdf:li xml:lang="en">{\rtf1 purpose of this document really think}</rdf:li></rdf:Alt></xmpDM:name></rdf:Description></rdf:li><rdf:li><rdf:Description xmpDM:startTime="681100" xmpDM:duration="2500" tscDM:valign="bottom" tscDM:halign="center" ><xmpDM:name><rdf:Alt><rdf:li xml:lang="en">{\rtf1 about it rhetorically before moving into}</rdf:li></rdf:Alt></xmpDM:name></rdf:Description></rdf:li><rdf:li><rdf:Description xmpDM:startTime="683600" xmpDM:duration="2766" tscDM:valign="bottom" tscDM:halign="center" ><xmpDM:name><rdf:Alt><rdf:li xml:lang="en">{\rtf1 things like organization and then style}</rdf:li></rdf:Alt></xmpDM:name></rdf:Description></rdf:li><rdf:li><rdf:Description xmpDM:startTime="686366" xmpDM:duration="3566" tscDM:valign="bottom" tscDM:halign="center" ><xmpDM:name><rdf:Alt><rdf:li xml:lang="en">{\rtf1 and tone and then copy editing and so as}</rdf:li></rdf:Alt></xmpDM:name></rdf:Description></rdf:li><rdf:li><rdf:Description xmpDM:startTime="689933" xmpDM:duration="2333" tscDM:valign="bottom" tscDM:halign="center" ><xmpDM:name><rdf:Alt><rdf:li xml:lang="en">{\rtf1 we move forward we&apos;re going to learn}</rdf:li></rdf:Alt></xmpDM:name></rdf:Description></rdf:li><rdf:li><rdf:Description xmpDM:startTime="692266" xmpDM:duration="5433" tscDM:valign="bottom" tscDM:halign="center" ><xmpDM:name><rdf:Alt><rdf:li xml:lang="en">{\rtf1 strategies to edit at the word level and}</rdf:li></rdf:Alt></xmpDM:name></rdf:Description></rdf:li><rdf:li><rdf:Description xmpDM:startTime="697700" xmpDM:duration="1233" tscDM:valign="bottom" tscDM:halign="center" ><xmpDM:name><rdf:Alt><rdf:li xml:lang="en">{\rtf1 in the sentence level and then the}</rdf:li></rdf:Alt></xmpDM:name></rdf:Description></rdf:li><rdf:li><rdf:Description xmpDM:startTime="698933" xmpDM:duration="3333" tscDM:valign="bottom" tscDM:halign="center" ><xmpDM:name><rdf:Alt><rdf:li xml:lang="en">{\rtf1 document level in that order but the}</rdf:li></rdf:Alt></xmpDM:name></rdf:Description></rdf:li><rdf:li><rdf:Description xmpDM:startTime="702266" xmpDM:duration="1633" tscDM:valign="bottom" tscDM:halign="center" ><xmpDM:name><rdf:Alt><rdf:li xml:lang="en">{\rtf1 hope is that you&apos;ll build your knowledge}</rdf:li></rdf:Alt></xmpDM:name></rdf:Description></rdf:li><rdf:li><rdf:Description xmpDM:startTime="703900" xmpDM:duration="2466" tscDM:valign="bottom" tscDM:halign="center" ><xmpDM:name><rdf:Alt><rdf:li xml:lang="en">{\rtf1 and your skills so that in the end}</rdf:li></rdf:Alt></xmpDM:name></rdf:Description></rdf:li><rdf:li><rdf:Description xmpDM:startTime="706366" xmpDM:duration="1266" tscDM:valign="bottom" tscDM:halign="center" ><xmpDM:name><rdf:Alt><rdf:li xml:lang="en">{\rtf1 you&apos;ll be able to actually flip the}</rdf:li></rdf:Alt></xmpDM:name></rdf:Description></rdf:li><rdf:li><rdf:Description xmpDM:startTime="707633" xmpDM:duration="2366" tscDM:valign="bottom" tscDM:halign="center" ><xmpDM:name><rdf:Alt><rdf:li xml:lang="en">{\rtf1 order and comprehensively edit from the}</rdf:li></rdf:Alt></xmpDM:name></rdf:Description></rdf:li><rdf:li><rdf:Description xmpDM:startTime="710000" xmpDM:duration="2500" tscDM:valign="bottom" tscDM:halign="center" ><xmpDM:name><rdf:Alt><rdf:li xml:lang="en">{\rtf1 beginning and then use those skills as}</rdf:li></rdf:Alt></xmpDM:name></rdf:Description></rdf:li><rdf:li><rdf:Description xmpDM:startTime="712500" xmpDM:duration="2000" tscDM:valign="bottom" tscDM:halign="center" ><xmpDM:name><rdf:Alt><rdf:li xml:lang="en">{\rtf1 you move along through the editorial}</rdf:li></rdf:Alt></xmpDM:name></rdf:Description></rdf:li><rdf:li><rdf:Description xmpDM:startTime="714500" xmpDM:duration="3400" tscDM:valign="bottom" tscDM:halign="center" ><xmpDM:name><rdf:Alt><rdf:li xml:lang="en">{\rtf1 process so that&apos;s sort of just a recap}</rdf:li></rdf:Alt></xmpDM:name></rdf:Description></rdf:li><rdf:li><rdf:Description xmpDM:startTime="717900" xmpDM:duration="2766" tscDM:valign="bottom" tscDM:halign="center" ><xmpDM:name><rdf:Alt><rdf:li xml:lang="en">{\rtf1 of copy editing versus comprehensive}</rdf:li></rdf:Alt></xmpDM:name></rdf:Description></rdf:li><rdf:li><rdf:Description xmpDM:startTime="720666" xmpDM:duration="1866" tscDM:valign="bottom" tscDM:halign="center" ><xmpDM:name><rdf:Alt><rdf:li xml:lang="en">{\rtf1 editing it hopefully gives you a better}</rdf:li></rdf:Alt></xmpDM:name></rdf:Description></rdf:li><rdf:li><rdf:Description xmpDM:startTime="722533" xmpDM:duration="2400" tscDM:valign="bottom" tscDM:halign="center" ><xmpDM:name><rdf:Alt><rdf:li xml:lang="en">{\rtf1 idea of where we&apos;re moving in this}</rdf:li></rdf:Alt></xmpDM:name></rdf:Description></rdf:li><rdf:li><rdf:Description xmpDM:startTime="724933" xmpDM:duration="2300" tscDM:valign="bottom" tscDM:halign="center" ><xmpDM:name><rdf:Alt><rdf:li xml:lang="en">{\rtf1 course}</rdf:li></rdf:Alt></xmpDM:name></rdf:Description></rdf:li></rdf:Seq></xmpDM:markers><tsc:fgColor xmpG:red="255" xmpG:green="255" xmpG:blue="255" xmpG:mode="RGB" ></tsc:fgColor><tsc:bgColor xmpG:red="0" xmpG:green="0" xmpG:blue="0" xmpG:mode="RGB" ></tsc:bgColor></rdf:Description></rdf:li><rdf:li><rdf:Description xmpDM:trackType="TableOfContents" xmpDM:trackName="Table of Contents" xmpDM:frameRate="f1000" tscDM:image="" tscDM:tocCellLayout="both" ><xmpDM:markers><rdf:Seq><rdf:li><rdf:Description xmpDM:name="Levels of Editing" xmpDM:startTime="27433" tscDM:image="TocThumbnails.png" tscDM:imageindex="0" tscDM:imageoffset="0" tscDM:imagerect="0,0,200,124" ></rdf:Description></rdf:li><rdf:li><rdf:Description xmpDM:name="Editing Continuum" xmpDM:startTime="64400" tscDM:image="TocThumbnails.png" tscDM:imageindex="1" tscDM:imageoffset="1" tscDM:imagerect="200,0,200,124" ></rdf:Description></rdf:li><rdf:li><rdf:Description xmpDM:name="Preview of style and tone" xmpDM:startTime="118600" tscDM:image="TocThumbnails.png" tscDM:imageindex="2" tscDM:imageoffset="2" tscDM:imagerect="400,0,200,124" ></rdf:Description></rdf:li><rdf:li><rdf:Description xmpDM:name="Editing for organization example" xmpDM:startTime="353966" tscDM:image="TocThumbnails.png" tscDM:imageindex="3" tscDM:imageoffset="3" tscDM:imagerect="600,0,200,124" ></rdf:Description></rdf:li><rdf:li><rdf:Description xmpDM:name="Strategies for editing" xmpDM:startTime="609733" tscDM:image="TocThumbnails.png" tscDM:imageindex="4" tscDM:imageoffset="4" tscDM:imagerect="800,0,200,124" ></rdf:Description></rdf:li></rdf:Seq></xmpDM:markers></rdf:Description></rdf:li></rdf:Bag></xmpDM:Tracks><tscDM:controller><rdf:Description xmpDM:name="tscplayer" ><tscDM:parameters><rdf:Bag><rdf:li xmpDM:name="autohide" xmpDM:value="true" ></rdf:li><rdf:li xmpDM:name="autoplay" xmpDM:value="false" ></rdf:li><rdf:li xmpDM:name="backgroundcolor" xmpDM:value="000000" ></rdf:li><rdf:li xmpDM:name="captionsenabled" xmpDM:value="false" ></rdf:li><rdf:li xmpDM:name="endaction" xmpDM:value="stop" ></rdf:li><rdf:li xmpDM:name="endactionparam" xmpDM:value="true" ></rdf:li><rdf:li xmpDM:name="locale" xmpDM:value="en-US" ></rdf:li><rdf:li xmpDM:name="searchable" xmpDM:value="true" ></rdf:li><rdf:li xmpDM:name="sidebarenabled" xmpDM:value="false" ></rdf:li><rdf:li xmpDM:name="sidebarlocation" xmpDM:value="left" ></rdf:li><rdf:li xmpDM:name="unicodeenabled" xmpDM:value="false" ></rdf:li></rdf:Bag></tscDM:parameters><tscDM:controllerText><rdf:Bag><rdf:li><rdf:Description xmp:label="localSecurityError" ><tscDM:localizedText><rdf:Alt><rdf:li xml:lang="en-US">Certain features in your video are currently disabled due to Local Network Security. These features work correctly when the video is played from a Website or Server.</rdf:li></rdf:Alt></tscDM:localizedText></rdf:Description></rdf:li><rdf:li><rdf:Description xmp:label="replayButtonText" ><tscDM:localizedText><rdf:Alt><rdf:li xml:lang="en-US">Replay</rdf:li></rdf:Alt></tscDM:localizedText></rdf:Description></rdf:li><rdf:li><rdf:Description xmp:label="resultText" ><tscDM:localizedText><rdf:Alt><rdf:li xml:lang="en-US">Results Found</rdf:li></rdf:Alt></tscDM:localizedText></rdf:Description></rdf:li><rdf:li><rdf:Description xmp:label="searchFullscreenText" ><tscDM:localizedText><rdf:Alt><rdf:li xml:lang="en-US">Search disabled in full screen mode</rdf:li></rdf:Alt></tscDM:localizedText></rdf:Description></rdf:li><rdf:li><rdf:Description xmp:label="searchText" ><tscDM:localizedText><rdf:Alt><rdf:li xml:lang="en-US">Search</rdf:li></rdf:Alt></tscDM:localizedText></rdf:Description></rdf:li></rdf:Bag></tscDM:controllerText></rdf:Description></tscDM:controller><tscDM:contentList><rdf:Description><tscDM:files><rdf:Seq><rdf:li xmpDM:name="1" xmpDM:value="copyediting vs comprehensive editing.mp4"></rdf:li><rdf:li xmpDM:name="2" xmpDM:value="TocThumbnails.png"></rdf:li></rdf:Seq></tscDM:files></rdf:Description></tscDM:contentList></rdf:Description></rdf:RDF></x:xmpmeta>